prac/fisqr/FpAdd.v
//--------------------------------------------------------------------
// Author: Omkar Girish Kamath (201EC140)
// Date: October 1st, 2023
// Module Name: FpAdd
// Module Description: Implements the custom 27-bit floating point
//                     adder where MSB is sign bit, next 8-bits are
//                     exponent in excess 127 and last 18-bits are ma-
//                     ntissa.
//--------------------------------------------------------------------

`define SIGN 26
`define EXP 25:18
`define MANT 17:0


module FpAdd (
              clk,             // replace string with clock
              in1,          // replace string with fp_in1
              in2,          // replace string with fp_in2
              sum,          // replace string with fp_sum
              rst
              );

   //--------------------------------------------------------------------
   // Inputs
   //--------------------------------------------------------------------
   input wire clk;
   input wire [26:0] in1;
   input wire [26:0] in2;
   input wire        rst;
   
   //--------------------------------------------------------------------
   // Outputs
   //--------------------------------------------------------------------
   output reg [26:0] sum;

   //--------------------------------------------------------------------
   // Internals
   //--------------------------------------------------------------------
   parameter sign = 26;
   parameter ex_end = 25;
   parameter ex_st = 18;
   parameter ma_end = 17;
   parameter ma_st = 0;

   //--------------------------------------------------------------------
   // First Stage
   //--------------------------------------------------------------------
   
   //--------------------------------------------------------------------
   // Finding greater number among the 2
   //--------------------------------------------------------------------
   reg [`SIGN:0] greater;
   reg [`SIGN:0] smaller;

   always @(*)
     begin
        if (in1[`EXP] > in2[`EXP])
          begin
             greater <= in1;
             smaller <= in2;
          end
        else
          if (in1[`EXP] == in2[`EXP] && in1[`MANT] > in2[`MANT])
            begin
               greater <= in1;
               smaller <= in2;
            end
          else
            begin
               greater <= in2;
               smaller <= in1;
            end
     end // always @ (*)
   
   
   //--------------------------------------------------------------------
   // Net smaller value for arithmetic
   //--------------------------------------------------------------------
   reg [18:0] net_small;
   wire [`EXP] small_shift;
   
   assign small_shift = greater[`EXP] - smaller[`EXP];
   
   always @(*)
     begin
        if (greater[`EXP] - smaller[`EXP] <= 5'd18)
          begin
             net_small <= {1'b1,smaller[`MANT]} >> (small_shift);
          end
        else
          begin
             net_small <= 'b0;
          end
     end // always @ (*)


   //--------------------------------------------------------------------
   // Pipeline Register's
   //--------------------------------------------------------------------
   reg [`SIGN:0] gr;
   reg [19:0] sm;
   reg [`EXP]    net_expt;
   reg [`EXP]    sm_shift;
   
   always @(posedge clk or negedge rst)
     begin
        if (rst == 'b0)
          begin
             gr <= 'b0;
             sm <= 'b0;
             net_expt <= 'b0;
             sm_shift <= 'b0;
          end 
        else
           begin
             gr <= greater;
             sm <= {smaller[`SIGN],net_small}; // check for sm
             net_expt <= greater[`EXP];
             sm_shift <= small_shift;
          end    
     end

   
   //--------------------------------------------------------------------
   // Second Stage
   //--------------------------------------------------------------------
   
   //--------------------------------------------------------------------
   // Deciding Addition or Subtraction
   //--------------------------------------------------------------------
   wire sub;
   assign sub = (gr[`SIGN] ^ sm[19]);
   

   //--------------------------------------------------------------------
   // Addition
   //--------------------------------------------------------------------
   
   //--------------------------------------------------------------------
   // Addition Output
   //--------------------------------------------------------------------
   reg [19:0] add_out;
   
   always @(*)
      begin
         add_out <= ({1'b1,gr[`MANT]} + {sm[18:0]});
      end


   //--------------------------------------------------------------------
   // net exponent adder if carry generated in addition
   //--------------------------------------------------------------------
   reg [`EXP] expt_carry;

   always @(*)
     begin
        expt_carry <= net_expt + {7'b0,add_out[19]};
     end


   //--------------------------------------------------------------------
   // result from the whole flow if sign bits of both numbers are equal
   // i.e addition of their magnitudes
   //--------------------------------------------------------------------
   reg [26:0] add_result;
   
   wire [17:0] final_add = (add_out[19]) ? 
               {add_out[18:1]} : add_out[17:0];
   

   always @(*)
     begin
        add_result <= {gr[`SIGN],expt_carry,final_add};
     end // always @ (*)

   
   //--------------------------------------------------------------------
   // Subtraction
   //--------------------------------------------------------------------
   
   //--------------------------------------------------------------------
   // Subtraction Output
   //--------------------------------------------------------------------
   reg [18:0] sub_out;

   always @(*)
     begin
        sub_out <= {1'b1,gr[`MANT]} - sm[`MANT];
     end

   //--------------------------------------------------------------------
   // Exponent Difference after subtraction Generator
   //--------------------------------------------------------------------
   reg [4:0] sub_shift;
      always @(*)
     begin
        casex (sub_out)
          19'b1XXXXXXXXXXXXXXXXXX: sub_shift <= 5'd0;
          19'b01XXXXXXXXXXXXXXXXX: sub_shift <= 5'd1;
          19'b001XXXXXXXXXXXXXXXX: sub_shift <= 5'd2;
          19'b0001XXXXXXXXXXXXXXX: sub_shift <= 5'd3;
          19'b00001XXXXXXXXXXXXXX: sub_shift <= 5'd4;
          19'b000001XXXXXXXXXXXXX: sub_shift <= 5'd5;
          19'b0000001XXXXXXXXXXXX: sub_shift <= 5'd6;
          19'b00000001XXXXXXXXXXX: sub_shift <= 5'd7;
          19'b000000001XXXXXXXXXX: sub_shift <= 5'd8;
          19'b0000000001XXXXXXXXX: sub_shift <= 5'd9;
          19'b00000000001XXXXXXXX: sub_shift <= 5'd10;
          19'b000000000001XXXXXXX: sub_shift <= 5'd11;
          19'b0000000000001XXXXXX: sub_shift <= 5'd12;
          19'b00000000000001XXXXX: sub_shift <= 5'd13;
          19'b000000000000001XXXX: sub_shift <= 5'd14;
          19'b0000000000000001XXX: sub_shift <= 5'd15;
          19'b00000000000000001XX: sub_shift <= 5'd16;
          19'b000000000000000001X: sub_shift <= 5'd17;
          19'b0000000000000000001: sub_shift <= 5'd18;
          19'b0000000000000000000: sub_shift <= 5'd19;
          default:                sub_shift <= 5'd0;
        endcase
     end // always @ (*)

  
   //--------------------------------------------------------------------
   // Calculating net exponent
   //--------------------------------------------------------------------
   reg [7:0] sub_expt;
   
   always @(*)
     begin
        sub_expt <= net_expt - {3'b0,sub_shift};
     end
   

   //--------------------------------------------------------------------
   // Calculating Final Subtraction Out after shift
   //--------------------------------------------------------------------
   reg [17:0] final_sub;
   reg [18:0] temp_sub;
   always @(*)
     begin
        temp_sub <= (sub_out << sub_shift);
        final_sub <= temp_sub[17:0];
     end
   //--------------------------------------------------------------------
   // Calculating Final Subtraction Result
   //--------------------------------------------------------------------
   reg [26:0] sub_result;

   always @(*)
     begin
        sub_result <= {gr[`SIGN],sub_expt,final_sub};
     end

   //--------------------------------------------------------------------
   // Calculating Final Subtraction Result
   //--------------------------------------------------------------------
   always @(*)
     begin
        if (sub)
          begin
             sum <= sub_result;
          end
        else
          begin
             sum <= add_result;
          end
     end

   //--------------------------------------------------------------------
   // Test code (not part of the RTL)
   //--------------------------------------------------------------------
   // always @(*)
   //   begin
   //      sum <= add_result;
   //  end
   wire [18:0] sm_mant = sm[18:0];
   wire [18:0] gr_mant = {1'b1,gr[`MANT]};
   
endmodule

prac/FpAdd_tb.v
module FpAdd_tb;
   reg [26:0] tst_in1;
   reg [26:0] tst_in2;
   reg        tst_clk;
   reg        tst_rst;
   wire [26:0] tst_out;
   reg [31:0]  fh;
   reg [31:0]  oh;
   reg [31:0]  file_result;
   integer     count;
   integer     total;
   
   reg [26:0]  vec1 [1023:0];
   reg [26:0]  vec2 [1023:0];
   
   initial
     begin
        fh = $fopen("/home/omkar/projects/grav_sim/test/Fp_Add_tstvec.txt","r");
        //oh = $fopen("../run/FpAddtemp.txt","w");
     end

   
   FpAdd dut (
              .clk(tst_clk),
              .rst(tst_rst),
              .in1(tst_in1),
              .in2(tst_in2),
              .sum(tst_out)
              );
   
   always
     begin
        tst_clk <= 1'b1;
        #5;
        tst_clk <= 1'b0;
        #5;
     end
   
   always @(posedge tst_clk)
     begin
        if (tst_rst == 'b1)
          begin
             tst_in1 <= vec1[count];
             tst_in2 <= vec2[count];
             $display("%b",tst_out);
             count <= count + 1;
             if (count == total)
               begin
                  $finish;
               end
          end
     end
   


   
   initial
     begin
        $dumpvars;
        count = 0;
        while (!$feof(fh))
          begin
             file_result = $fscanf(fh,"%b %b",vec1[count],vec2[count]);
             count = count + 1;
          end
        total <= count;
        count <= 0;
        tst_rst = 'b0;
        repeat (5)
          begin
             @ (posedge tst_clk);
          end
        //#50;
        tst_rst <= 'b1;
        
        #1000;
        $finish;
        
        
     end

endmodule

prac/dump.vcd
$date
	Sat Oct 21 03:39:20 2023
$end
$version
	Icarus Verilog
$end
$timescale
	1s
$end
$scope module FpAdd_tb $end
$var wire 27 ! tst_out [26:0] $end
$var reg 32 " fh [31:0] $end
$var reg 32 # file_result [31:0] $end
$var reg 1 $ tst_clk $end
$var reg 27 % tst_in1 [26:0] $end
$var reg 27 & tst_in2 [26:0] $end
$var reg 1 ' tst_rst $end
$var integer 32 ( count [31:0] $end
$var integer 32 ) total [31:0] $end
$scope module dut $end
$var wire 1 $ clk $end
$var wire 27 * in1 [26:0] $end
$var wire 27 + in2 [26:0] $end
$var wire 1 ' rst $end
$var wire 1 , sub $end
$var wire 8 - small_shift [25:18] $end
$var wire 19 . sm_mant [18:0] $end
$var wire 19 / gr_mant [18:0] $end
$var wire 18 0 final_add [17:0] $end
$var reg 20 1 add_out [19:0] $end
$var reg 27 2 add_result [26:0] $end
$var reg 8 3 expt_carry [25:18] $end
$var reg 18 4 final_sub [17:0] $end
$var reg 27 5 gr [26:0] $end
$var reg 27 6 greater [26:0] $end
$var reg 8 7 net_expt [25:18] $end
$var reg 19 8 net_small [18:0] $end
$var reg 20 9 sm [19:0] $end
$var reg 8 : sm_shift [25:18] $end
$var reg 27 ; smaller [26:0] $end
$var reg 8 < sub_expt [7:0] $end
$var reg 19 = sub_out [18:0] $end
$var reg 27 > sub_result [26:0] $end
$var reg 5 ? sub_shift [4:0] $end
$var reg 27 @ sum [26:0] $end
$var reg 19 A temp_sub [18:0] $end
$upscope $end
$upscope $end
$enddefinitions $end
#0
$dumpvars
b1000000000000000000 A
b0 @
b0 ?
b0 >
b1000000000000000000 =
b0 <
bx ;
b0 :
b0 9
bx 8
b0 7
bx 6
b0 5
b0 4
b0 3
b0 2
b1000000000000000000 1
b0 0
b1000000000000000000 /
b0 .
bx -
0,
bx +
bx *
b1100101 )
b0 (
0'
bx &
bx %
1$
b0 #
b10000000000000000000000000000011 "
b0 !
$end
#5
0$
#10
1$
#15
0$
#20
1$
#25
0$
#30
1$
#35
0$
#40
1'
1$
#45
0$
#50
bx 4
bx A
bx !
bx @
b0 8
bx 0
b11110 -
bx <
bx 3
bx >
bx 1
bx =
bx 2
b110111110110100011001011001 ;
b11011100110110100001001111 6
x,
bx .
b1xxxxxxxxxxxxxxxxxx /
bx :
bx 7
bx 9
bx 5
b1 (
b11011100110110100001001111 &
b11011100110110100001001111 +
b110111110110100011001011001 %
b110111110110100011001011001 *
1$
#55
0$
#60
b110110100001001111 4
b1110110100001001111 A
b11011100 3
b11011100110110100001001111 !
b11011100110110100001001111 @
b110110100001001111 0
b1000011 -
b11011100 <
b11011100110110100001001111 >
b1110110100001001111 =
b1110110100001001111 1
b11011100110110100001001111 2
b101010100001101010100011101 ;
b10010111001111011000111101 6
1,
b0 .
b1110110100001001111 /
b11110 :
b11011100 7
b10000000000000000000 9
b11011100110110100001001111 5
b10 (
b101010100001101010100011101 &
b101010100001101010100011101 +
b10010111001111011000111101 %
b10010111001111011000111101 *
1$
#65
0$
#70
b10010111001111011000111101 !
b10010111001111011000111101 @
b1111011000111101 4
b10010111001111011000111101 >
b10010111001111011000111101 2
b1001111011000111101 A
b1111011000111101 0
b11100110 -
b10010111 <
b10010111 3
b1001111011000111101 1
b1001111011000111101 =
b100010011100111011101110101 ;
b111111001100100111000010100 6
b1001111011000111101 /
b1000011 :
b10010111 7
b10010111001111011000111101 5
b11 (
b100010011100111011101110101 &
b100010011100111011101110101 +
b111111001100100111000010100 %
b111111001100100111000010100 *
1$
#75
0$
#80
b100100111000010100 4
b1100100111000010100 A
b111111001100100111000010100 !
b111111001100100111000010100 @
b100100111000010100 0
b1100010 -
b11111001 <
b11111001 3
b111111001100100111000010100 >
b1100100111000010100 =
b1100100111000010100 1
b111111001100100111000010100 2
b100010111010000111011001111 ;
b1111001000010000101010011 6
0,
b1100100111000010100 /
b11100110 :
b11111001 7
b111111001100100111000010100 5
b100 (
b100010111010000111011001111 &
b100010111010000111011001111 +
b1111001000010000101010011 %
b1111001000010000101010011 *
1$
#85
0$
#90
b10000101010011 4
b1000010000101010011 A
b1111001000010000101010011 !
b1111001000010000101010011 @
b10000101010011 0
b10110110 -
b1111001 <
b1111001 3
b1111001000010000101010011 >
b1000010000101010011 1
b1000010000101010011 =
b1111001000010000101010011 2
b111111111110101111111000 ;
b111110101011000000101111010 6
1,
b1000010000101010011 /
b1100010 :
b1111001 7
b1111001000010000101010011 5
b101 (
b111111111110101111111000 &
b111111111110101111111000 +
b111110101011000000101111010 %
b111110101011000000101111010 *
1$
#95
0$
#100
b11000000101111010 4
b1011000000101111010 A
b111110101011000000101111010 !
b111110101011000000101111010 @
b11000000101111010 0
b10100110 -
b11110101 <
b11110101 3
b111110101011000000101111010 >
b1011000000101111010 =
b1011000000101111010 1
b111110101011000000101111010 2
b101010010011001100111100110 ;
b11111000110111000111110000 6
b1011000000101111010 /
b10110110 :
b11110101 7
b0 9
b111110101011000000101111010 5
b110 (
b101010010011001100111100110 &
b101010010011001100111100110 +
b11111000110111000111110000 %
b11111000110111000111110000 *
1$
#105
0$
#110
b110111000111110000 4
b1110111000111110000 A
b11111000110111000111110000 !
b11111000110111000111110000 @
b110111000111110000 0
b10000110 -
b11111000 <
b11111000 3
b11111000110111000111110000 >
b1110111000111110000 1
b1110111000111110000 =
b11111000110111000111110000 2
b1110000011110010110111010 ;
b111110110000111001110110101 6
b1110111000111110000 /
b10100110 :
b11111000 7
b10000000000000000000 9
b11111000110111000111110000 5
b111 (
b111110110000111001110110101 &
b111110110000111001110110101 +
b1110000011110010110111010 %
b1110000011110010110111010 *
1$
#115
0$
#120
b111001110110101 4
b1000111001110110101 A
b111110110000111001110110101 !
b111110110000111001110110101 @
b111001110110101 0
b11101000 -
b11110110 <
b11110110 3
b111110110000111001110110101 >
b1000111001110110101 =
b1000111001110110101 1
b111110110000111001110110101 2
b10101111000100010110101 ;
b11111101010001111100011010 6
b1000111001110110101 /
b10000110 :
b11110110 7
b0 9
b111110110000111001110110101 5
b1000 (
b10101111000100010110101 &
b10101111000100010110101 +
b11111101010001111100011010 %
b11111101010001111100011010 *
1$
#125
0$
#130
b10001111100011010 4
b1010001111100011010 A
b11111101010001111100011010 !
b11111101010001111100011010 @
b10001111100011010 0
b1000101 -
b11111101 <
b11111101 3
b11111101010001111100011010 >
b1010001111100011010 1
b1010001111100011010 =
b11111101010001111100011010 2
b10100001010011110110000011 ;
b111100110001011011001111100 6
0,
b1010001111100011010 /
b11101000 :
b11111101 7
b11111101010001111100011010 5
b1001 (
b111100110001011011001111100 &
b111100110001011011001111100 +
b10100001010011110110000011 %
b10100001010011110110000011 *
1$
#135
0$
#140
b1011011001111100 4
b1001011011001111100 A
b111100110001011011001111100 !
b111100110001011011001111100 @
b1011011001111100 0
b1100110 -
b11100110 <
b11100110 3
b111100110001011011001111100 >
b1001011011001111100 =
b1001011011001111100 1
b111100110001011011001111100 2
b101010111100110000011011110 ;
b110111101110000001110011111 6
1,
b1001011011001111100 /
b1000101 :
b11100110 7
b111100110001011011001111100 5
b1010 (
b110111101110000001110011111 &
b110111101110000001110011111 +
b101010111100110000011011110 %
b101010111100110000011011110 *
1$
#145
0$
#150
b110111101110000001110011111 !
b110111101110000001110011111 @
b110000001110011111 4
b110111101110000001110011111 >
b110111101110000001110011111 2
b1110000001110011111 A
b110000001110011111 0
b11100001 -
b10111101 <
b10111101 3
b1110000001110011111 1
b1110000001110011111 =
b10000100001110011000000 ;
b111110001001100111110001101 6
0,
b1110000001110011111 /
b1100110 :
b10111101 7
b10000000000000000000 9
b110111101110000001110011111 5
b1011 (
b111110001001100111110001101 &
b111110001001100111110001101 +
b10000100001110011000000 %
b10000100001110011000000 *
1$
#155
0$
#160
b111110001001100111110001101 !
b111110001001100111110001101 @
b1100111110001101 4
b101010000 8
b111110001001100111110001101 >
b111110001001100111110001101 2
b1001100111110001101 A
b1100111110001101 0
b1010 -
b11110001 <
b11110001 3
b1001100111110001101 =
b1001100111110001101 1
b10010100001011011011 ;
b100001100010101000100110001 6
1,
b1001100111110001101 /
b11100001 :
b11110001 7
b0 9
b111110001001100111110001101 5
b1100 (
b100001100010101000100110001 &
b100001100010101000100110001 +
b10010100001011011011 %
b10010100001011011011 *
1$
#165
0$
#170
b100001100010100111111100001 !
b100001100010100111111100001 @
b10100111111100001 4
b100001100010100111111100001 >
b100001100010101001010000001 2
b1010100111111100001 A
b0 8
b10101001010000001 0
b10011001 -
b1100 <
b1100 3
b1010101001010000001 1
b1010100111111100001 =
b100010010110101000111101000 ;
b10101011001010111100100101 6
b101010000 .
b1010101000100110001 /
b1010 :
b1100 7
b101010000 9
b100001100010101000100110001 5
b1101 (
b10101011001010111100100101 &
b10101011001010111100100101 +
b100010010110101000111101000 %
b100010010110101000111101000 *
1$
#175
0$
#180
b1010111100100101 4
b1001010111100100101 A
b10101011001010111100100101 !
b10101011001010111100100101 @
b1010111100100101 0
b1101110 -
b10101011 <
b10101011 3
b10101011001010111100100101 >
b1001010111100100101 =
b1001010111100100101 1
b10101011001010111100100101 2
b110000000000000000110000010 ;
b11101110110010001011101000 6
b0 .
b1001010111100100101 /
b10011001 :
b10101011 7
b10000000000000000000 9
b10101011001010111100100101 5
b1110 (
b11101110110010001011101000 &
b11101110110010001011101000 +
b110000000000000000110000010 %
b110000000000000000110000010 *
1$
#185
0$
#190
b11101110110010001011101000 !
b11101110110010001011101000 @
b110010001011101000 4
b11101110110010001011101000 >
b11101110110010001011101000 2
b1110010001011101000 A
b110010001011101000 0
b10000110 -
b11101110 <
b11101110 3
b1110010001011101000 1
b1110010001011101000 =
b100101010000011011010001100 ;
b10110000111101100111011001 6
b1110010001011101000 /
b1101110 :
b11101110 7
b11101110110010001011101000 5
b1111 (
b10110000111101100111011001 &
b10110000111101100111011001 +
b100101010000011011010001100 %
b100101010000011011010001100 *
1$
#195
0$
#200
b10110000111101100111011001 !
b10110000111101100111011001 @
b111101100111011001 4
b10110000111101100111011001 >
b10110000111101100111011001 2
b1111101100111011001 A
b111101100111011001 0
b10100111 -
b10110000 <
b10110000 3
b1111101100111011001 =
b1111101100111011001 1
b100000111111010001100010011 ;
b110101110011001101011110000 6
b1111101100111011001 /
b10000110 :
b10110000 7
b10110000111101100111011001 5
b10000 (
b100000111111010001100010011 &
b100000111111010001100010011 +
b110101110011001101011110000 %
b110101110011001101011110000 *
1$
#205
0$
#210
b11001101011110000 4
b1011001101011110000 A
b110101110011001101011110000 !
b110101110011001101011110000 @
b11001101011110000 0
b11001010 -
b10101110 <
b10101110 3
b110101110011001101011110000 >
b1011001101011110000 1
b1011001101011110000 =
b110101110011001101011110000 2
b100011011100100000110101011 ;
b11100101100100100001100011 6
0,
b1011001101011110000 /
b10100111 :
b10101110 7
b110101110011001101011110000 5
b10001 (
b11100101100100100001100011 &
b11100101100100100001100011 +
b100011011100100000110101011 %
b100011011100100000110101011 *
1$
#215
0$
#220
b100100100001100011 4
b1100100100001100011 A
b11100101100100100001100011 !
b11100101100100100001100011 @
b100100100001100011 0
b1101111 -
b11100101 <
b11100101 3
b11100101100100100001100011 >
b1100100100001100011 =
b1100100100001100011 1
b11100101100100100001100011 2
b101011000011101001010000100 ;
b11000111111001011100010011 6
1,
b1100100100001100011 /
b11001010 :
b11100101 7
b11100101100100100001100011 5
b10010 (
b101011000011101001010000100 &
b101011000011101001010000100 +
b11000111111001011100010011 %
b11000111111001011100010011 *
1$
#225
0$
#230
b11000111111001011100010011 !
b11000111111001011100010011 @
b111001011100010011 4
b11000111111001011100010011 >
b11000111111001011100010011 2
b1111001011100010011 A
b111001011100010011 0
b110000 -
b11000111 <
b11000111 3
b1111001011100010011 1
b1111001011100010011 =
b100000101101110101011010101 ;
b110101000101110011001000 6
b1111001011100010011 /
b1101111 :
b11000111 7
b11000111111001011100010011 5
b10011 (
b100000101101110101011010101 &
b100000101101110101011010101 +
b110101000101110011001000 %
b110101000101110011001000 *
1$
#235
0$
#240
b110101000101110011001000 !
b110101000101110011001000 @
b101110011001000 4
b110101000101110011001000 >
b110101000101110011001000 2
b1000101110011001000 A
b101110011001000 0
b110011 -
b110101 <
b110101 3
b1000101110011001000 =
b1000101110011001000 1
b1101001101001111000110100 ;
b10011100111001001100101011 6
b1000101110011001000 /
b110000 :
b110101 7
b110101000101110011001000 5
b10100 (
b1101001101001111000110100 &
b1101001101001111000110100 +
b10011100111001001100101011 %
b10011100111001001100101011 *
1$
#245
0$
#250
b10011100111001001100101011 !
b10011100111001001100101011 @
b111001001100101011 4
b10011100111001001100101011 >
b10011100111001001100101011 2
b1111001001100101011 A
b111001001100101011 0
b10011010 -
b10011100 <
b10011100 3
b1111001001100101011 1
b1111001001100101011 =
b110000111010000011001101 ;
b11001010010011000110100100 6
0,
b1111001001100101011 /
b110011 :
b10011100 7
b0 9
b10011100111001001100101011 5
b10101 (
b11001010010011000110100100 &
b11001010010011000110100100 +
b110000111010000011001101 %
b110000111010000011001101 *
1$
#255
0$
#260
b11001010010011000110100100 !
b11001010010011000110100100 @
b10011000110100100 4
b11001010010011000110100100 >
b11001010010011000110100100 2
b1010011000110100100 A
b10011000110100100 0
b1000000 -
b11001010 <
b11001010 3
b1010011000110100100 =
b1010011000110100100 1
b1010100001100111101101110 ;
b110010100001000111111111110 6
b1010011000110100100 /
b10011010 :
b11001010 7
b11001010010011000110100100 5
b10110 (
b110010100001000111111111110 &
b110010100001000111111111110 +
b1010100001100111101101110 %
b1010100001100111101101110 *
1$
#265
0$
#270
b1000111111111110 4
b1001000111111111110 A
b110010100001000111111111110 !
b110010100001000111111111110 @
b1000111111111110 0
b11011100 -
b10010100 <
b10010100 3
b110010100001000111111111110 >
b1001000111111111110 1
b1001000111111111110 =
b110010100001000111111111110 2
b10000111110001100100000 ;
b11101100100110100001101010 6
1,
b1001000111111111110 /
b1000000 :
b10010100 7
b110010100001000111111111110 5
b10111 (
b11101100100110100001101010 &
b11101100100110100001101010 +
b10000111110001100100000 %
b10000111110001100100000 *
1$
#275
0$
#280
b100110100001101010 4
b1100110100001101010 A
b11101100100110100001101010 !
b11101100100110100001101010 @
b100110100001101010 0
b1011101 -
b11101100 <
b11101100 3
b11101100100110100001101010 >
b1100110100001101010 =
b1100110100001101010 1
b11101100100110100001101010 2
b110011010111101000000110000 ;
b111110111010011101011100110 6
0,
b1100110100001101010 /
b11011100 :
b11101100 7
b11101100100110100001101010 5
b11000 (
b111110111010011101011100110 &
b111110111010011101011100110 +
b110011010111101000000110000 %
b110011010111101000000110000 *
1$
#285
0$
#290
b10011101011100110 4
b1010011101011100110 A
b111110111010011101011100110 !
b111110111010011101011100110 @
b10011101011100110 0
b110110 -
b11110111 <
b11110111 3
b111110111010011101011100110 >
b1010011101011100110 1
b1010011101011100110 =
b111110111010011101011100110 2
b1100000111011101101001100 ;
b10010110011010101001010111 6
b1010011101011100110 /
b1011101 :
b11110111 7
b10000000000000000000 9
b111110111010011101011100110 5
b11001 (
b1100000111011101101001100 &
b1100000111011101101001100 +
b10010110011010101001010111 %
b10010110011010101001010111 *
1$
#295
0$
#300
b11010101001010111 4
b1011010101001010111 A
b10010110011010101001010111 !
b10010110011010101001010111 @
b11010101001010111 0
b1000001 -
b10010110 <
b10010110 3
b10010110011010101001010111 >
b1011010101001010111 =
b1011010101001010111 1
b10010110011010101001010111 2
b1111100011000111111100111 ;
b110111101000011101111101010 6
b1011010101001010111 /
b110110 :
b10010110 7
b0 9
b10010110011010101001010111 5
b11010 (
b110111101000011101111101010 &
b110111101000011101111101010 +
b1111100011000111111100111 %
b1111100011000111111100111 *
1$
#305
0$
#310
b11101111101010 4
b1000011101111101010 A
b110111101000011101111101010 !
b110111101000011101111101010 @
b11101111101010 0
b1011011 -
b10111101 <
b10111101 3
b110111101000011101111101010 >
b1000011101111101010 1
b1000011101111101010 =
b110111101000011101111101010 2
b101111001001111100011000000 ;
b111010100011010100010011100 6
1,
b1000011101111101010 /
b1000001 :
b10111101 7
b110111101000011101111101010 5
b11011 (
b101111001001111100011000000 &
b101111001001111100011000000 +
b111010100011010100010011100 %
b111010100011010100010011100 *
1$
#315
0$
#320
b111010100011010100010011100 !
b111010100011010100010011100 @
b11010100010011100 4
b1010101001 8
b111010100011010100010011100 >
b111010100011010100010011100 2
b1011010100010011100 A
b11010100010011100 0
b1001 -
b11010100 <
b11010100 3
b1011010100010011100 =
b1011010100010011100 1
b101111010101001001010111 ;
b100111000000011111110010010 6
0,
b1011010100010011100 /
b1011011 :
b11010100 7
b10000000000000000000 9
b111010100011010100010011100 5
b11100 (
b100111000000011111110010010 &
b100111000000011111110010010 +
b101111010101001001010111 %
b101111010101001001010111 *
1$
#325
0$
#330
b100111000000011110011101001 !
b100111000000011110011101001 @
b11110011101001 4
b100111000000011110011101001 >
b100111000000100001000111011 2
b1000011110011101001 A
b0 8
b100001000111011 0
b1111111 -
b111000 <
b111000 3
b1000100001000111011 1
b1000011110011101001 =
b100001111100110101111101011 ;
b110001110101000111011101111 6
1,
b1010101001 .
b1000011111110010010 /
b1001 :
b111000 7
b1010101001 9
b100111000000011111110010010 5
b11101 (
b110001110101000111011101111 &
b110001110101000111011101111 +
b100001111100110101111101011 %
b100001111100110101111101011 *
1$
#335
0$
#340
b101000111011101111 4
b10 8
b110001110101000111011101111 >
b110001110101000111011101111 2
b1101000111011101111 A
b101000111011101111 0
b10001 -
b110001110101000111011101111 !
b110001110101000111011101111 @
b10001110 <
b10001110 3
b1101000111011101111 =
b1101000111011101111 1
b101101010001011001110110001 ;
b1111011101111011011101101 6
0,
b0 .
b1101000111011101111 /
b1111111 :
b10001110 7
b10000000000000000000 9
b110001110101000111011101111 5
b11110 (
b101101010001011001110110001 &
b101101010001011001110110001 +
b1111011101111011011101101 %
b1111011101111011011101101 *
1$
#345
0$
#350
b101111011011101011 4
b1101111011011101011 A
b1111011101111011011101011 !
b1111011101111011011101011 @
b0 8
b101111011011101111 0
b10010000 -
b1111011 <
b1111011 3
b1111011101111011011101011 >
b1101111011011101111 1
b1101111011011101011 =
b1111011101111011011101111 2
b101101000001000011111000010 ;
b11111000101000010010101100 6
1,
b10 .
b1101111011011101101 /
b10001 :
b1111011 7
b10000000000000000010 9
b1111011101111011011101101 5
b11111 (
b101101000001000011111000010 &
b101101000001000011111000010 +
b11111000101000010010101100 %
b11111000101000010010101100 *
1$
#355
0$
#360
b11111000101000010010101100 !
b11111000101000010010101100 @
b101000010010101100 4
b11111000101000010010101100 >
b11111000101000010010101100 2
b1101000010010101100 A
b101000010010101100 0
b10000111 -
b11111000 <
b11111000 3
b1101000010010101100 =
b1101000010010101100 1
b10000101001111001111000 ;
b10010111110011001010011101 6
b0 .
b1101000010010101100 /
b10010000 :
b11111000 7
b10000000000000000000 9
b11111000101000010010101100 5
b100000 (
b10010111110011001010011101 &
b10010111110011001010011101 +
b10000101001111001111000 %
b10000101001111001111000 *
1$
#365
0$
#370
b10010111110011001010011101 !
b10010111110011001010011101 @
b110011001010011101 4
b10010111110011001010011101 >
b10010111110011001010011101 2
b1110011001010011101 A
b110011001010011101 0
b1111111 -
b10010111 <
b10010111 3
b1110011001010011101 1
b1110011001010011101 =
b100001110001001110110000011 ;
b110001101110010101110000100 6
0,
b1110011001010011101 /
b10000111 :
b10010111 7
b0 9
b10010111110011001010011101 5
b100001 (
b100001110001001110110000011 &
b100001110001001110110000011 +
b110001101110010101110000100 %
b110001101110010101110000100 *
1$
#375
0$
#380
b110010101110000100 4
b1110010101110000100 A
b110001101110010101110000100 !
b110001101110010101110000100 @
b110010101110000100 0
b10011111 -
b10001101 <
b10001101 3
b110001101110010101110000100 >
b1110010101110000100 =
b1110010101110000100 1
b110001101110010101110000100 2
b110111100100111111100001 ;
b111010110100110001110010111 6
b1110010101110000100 /
b1111111 :
b10001101 7
b10000000000000000000 9
b110001101110010101110000100 5
b100010 (
b110111100100111111100001 &
b110111100100111111100001 +
b111010110100110001110010111 %
b111010110100110001110010111 *
1$
#385
0$
#390
b111010110100110001110010111 !
b111010110100110001110010111 @
b100110001110010111 4
b111010110100110001110010111 >
b111010110100110001110010111 2
b1100110001110010111 A
b100110001110010111 0
b1010001 -
b11010110 <
b11010110 3
b1100110001110010111 1
b1100110001110010111 =
b100000010110011011011000011 ;
b1010011111010111100101001 6
1,
b1100110001110010111 /
b10011111 :
b11010110 7
b0 9
b111010110100110001110010111 5
b100011 (
b100000010110011011011000011 &
b100000010110011011011000011 +
b1010011111010111100101001 %
b1010011111010111100101001 *
1$
#395
0$
#400
b111010111100101001 4
b1001 8
b1111010111100101001 A
b1010011111010111100101001 !
b1010011111010111100101001 @
b111010111100101001 0
b1111 -
b1010011 <
b1010011 3
b1010011111010111100101001 >
b1111010111100101001 =
b1111010111100101001 1
b1010011111010111100101001 2
b11010001001110110111010101 ;
b111100000101100010010011110 6
b1111010111100101001 /
b1010001 :
b1010011 7
b10000000000000000000 9
b1010011111010111100101001 5
b100100 (
b11010001001110110111010101 &
b11010001001110110111010101 +
b111100000101100010010011110 %
b111100000101100010010011110 *
1$
#405
0$
#410
b101100010010010101 4
b1101100010010010101 A
b111100000101100010010010101 !
b111100000101100010010010101 @
b0 8
b101100010010100111 0
b11100011 -
b11100000 <
b11100000 3
b111100000101100010010010101 >
b1101100010010100111 1
b1101100010010010101 =
b111100000101100010010100111 2
b100011000110000101110111110 ;
b11111011001011110011111001 6
b1001 .
b1101100010010011110 /
b1111 :
b11100000 7
b1001 9
b111100000101100010010011110 5
b100101 (
b11111011001011110011111001 &
b11111011001011110011111001 +
b100011000110000101110111110 %
b100011000110000101110111110 *
1$
#415
0$
