rtl/FpAdd.v
//--------------------------------------------------------------------
// Author: Omkar Girish Kamath (201EC140)
// Date: October 1st, 2023
// Module Name: FpAdd
// Module Description: Implements the custom 27-bit floating point
//                     adder where MSB is sign bit, next 8-bits are
//                     exponent in excess 127 and last 18-bits are ma-
//                     ntissa.
//--------------------------------------------------------------------

`define SIGN 26
`define EXP 25:18
`define MANT 17:0


module FpAdd (
              clk,             // replace string with clock
              in1,          // replace string with fp_in1
              in2,          // replace string with fp_in2
              sum,          // replace string with fp_sum
              rst
              );

   //--------------------------------------------------------------------
   // Inputs
   //--------------------------------------------------------------------
   input wire clk;
   input wire [26:0] in1;
   input wire [26:0] in2;
   input wire        rst;
   
   //--------------------------------------------------------------------
   // Outputs
   //--------------------------------------------------------------------
   output reg [26:0] sum;

   //--------------------------------------------------------------------
   // Internals
   //--------------------------------------------------------------------
   parameter sign = 26;
   parameter ex_end = 25;
   parameter ex_st = 18;
   parameter ma_end = 17;
   parameter ma_st = 0;

   //--------------------------------------------------------------------
   // First Stage
   //--------------------------------------------------------------------
   
   //--------------------------------------------------------------------
   // Finding greater number among the 2
   //--------------------------------------------------------------------
   reg [`SIGN:0] greater;
   reg [`SIGN:0] smaller;

   always @(*)
     begin
        if (in1[`EXP] > in2[`EXP])
          begin
             greater <= in1;
             smaller <= in2;
          end
        else
          if (in1[`EXP] == in2[`EXP] && in1[`MANT] > in2[`MANT])
            begin
               greater <= in1;
               smaller <= in2;
            end
          else
            begin
               greater <= in2;
               smaller <= in1;
            end
     end // always @ (*)
   
   
   //--------------------------------------------------------------------
   // Net smaller value for arithmetic
   //--------------------------------------------------------------------
   reg [18:0] net_small;
   wire [`EXP] small_shift;
   
   assign small_shift = greater[`EXP] - smaller[`EXP];
   
   always @(*)
     begin
        if (greater[`EXP] - smaller[`EXP] <= 5'd18)
          begin
             net_small <= {1'b1,smaller[`MANT]} >> (small_shift);
          end
        else
          begin
             net_small <= 'b0;
          end
     end // always @ (*)


   //--------------------------------------------------------------------
   // Pipeline Register's
   //--------------------------------------------------------------------
   reg [`SIGN:0] gr;
   reg [19:0] sm;
   reg [`EXP]    net_expt;
   reg [`EXP]    sm_shift;
   
   always @(posedge clk )
     begin
        if (rst == 'b0)
          begin
             gr <= 'b0;
             sm <= 'b0;
             net_expt <= 'b0;
             sm_shift <= 'b0;
          end 
        else
           begin
             gr <= greater;
             sm <= {smaller[`SIGN],net_small}; // check for sm
             net_expt <= greater[`EXP];
             sm_shift <= small_shift;
          end    
     end

   
   //--------------------------------------------------------------------
   // Second Stage
   //--------------------------------------------------------------------
   
   //--------------------------------------------------------------------
   // Deciding Addition or Subtraction
   //--------------------------------------------------------------------
   wire sub;
   assign sub = (gr[`SIGN] ^ sm[19]);
   

   //--------------------------------------------------------------------
   // Addition
   //--------------------------------------------------------------------
   
   //--------------------------------------------------------------------
   // Addition Output
   //--------------------------------------------------------------------
   reg [19:0] add_out;
   
   always @(*)
      begin
         add_out <= ({1'b1,gr[`MANT]} + {sm[18:0]});
      end


   //--------------------------------------------------------------------
   // net exponent adder if carry generated in addition
   //--------------------------------------------------------------------
   reg [`EXP] expt_carry;

   always @(*)
     begin
        expt_carry <= net_expt + {7'b0,add_out[19]};
     end


   //--------------------------------------------------------------------
   // result from the whole flow if sign bits of both numbers are equal
   // i.e addition of their magnitudes
   //--------------------------------------------------------------------
   reg [26:0] add_result;
   
   wire [17:0] final_add = (add_out[19]) ? 
               {add_out[18:1]} : add_out[17:0];
   

   always @(*)
     begin
        add_result <= {gr[`SIGN],expt_carry,final_add};
     end // always @ (*)

   
   //--------------------------------------------------------------------
   // Subtraction
   //--------------------------------------------------------------------
   
   //--------------------------------------------------------------------
   // Subtraction Output
   //--------------------------------------------------------------------
   reg [18:0] sub_out;

   always @(*)
     begin
        sub_out <= {1'b1,gr[`MANT]} - sm[18:0];
     end

   //--------------------------------------------------------------------
   // Exponent Difference after subtraction Generator
   //--------------------------------------------------------------------
   reg [4:0] sub_shift;
      always @(*)
     begin
        casex (sub_out)
          19'b1XXXXXXXXXXXXXXXXXX: sub_shift <= 5'd0;
          19'b01XXXXXXXXXXXXXXXXX: sub_shift <= 5'd1;
          19'b001XXXXXXXXXXXXXXXX: sub_shift <= 5'd2;
          19'b0001XXXXXXXXXXXXXXX: sub_shift <= 5'd3;
          19'b00001XXXXXXXXXXXXXX: sub_shift <= 5'd4;
          19'b000001XXXXXXXXXXXXX: sub_shift <= 5'd5;
          19'b0000001XXXXXXXXXXXX: sub_shift <= 5'd6;
          19'b00000001XXXXXXXXXXX: sub_shift <= 5'd7;
          19'b000000001XXXXXXXXXX: sub_shift <= 5'd8;
          19'b0000000001XXXXXXXXX: sub_shift <= 5'd9;
          19'b00000000001XXXXXXXX: sub_shift <= 5'd10;
          19'b000000000001XXXXXXX: sub_shift <= 5'd11;
          19'b0000000000001XXXXXX: sub_shift <= 5'd12;
          19'b00000000000001XXXXX: sub_shift <= 5'd13;
          19'b000000000000001XXXX: sub_shift <= 5'd14;
          19'b0000000000000001XXX: sub_shift <= 5'd15;
          19'b00000000000000001XX: sub_shift <= 5'd16;
          19'b000000000000000001X: sub_shift <= 5'd17;
          19'b0000000000000000001: sub_shift <= 5'd18;
          19'b0000000000000000000: sub_shift <= 5'd19;
          default:                sub_shift <= 5'd0;
        endcase
     end // always @ (*)

  
   //--------------------------------------------------------------------
   // Calculating net exponent
   //--------------------------------------------------------------------
   reg [7:0] sub_expt;
   
   always @(*)
     begin
        sub_expt <= net_expt - {3'b0,sub_shift};
     end
   

   //--------------------------------------------------------------------
   // Calculating Final Subtraction Out after shift
   //--------------------------------------------------------------------
   reg [17:0] final_sub;
   reg [18:0] temp_sub;
   always @(*)
     begin
        temp_sub <= (sub_out << sub_shift);
        final_sub <= temp_sub[17:0];
     end
   //--------------------------------------------------------------------
   // Calculating Final Subtraction Result
   //--------------------------------------------------------------------
   reg [26:0] sub_result;

   always @(*)
     begin
        sub_result <= {gr[`SIGN],sub_expt,final_sub};
     end

   //--------------------------------------------------------------------
   // Calculating Final Subtraction Result
   //--------------------------------------------------------------------
   always @(*)
     begin
        if (sub)
          begin
             sum <= sub_result;
          end
        else
          begin
             sum <= add_result;
          end
     end

   //--------------------------------------------------------------------
   // Test code (not part of the RTL)
   //--------------------------------------------------------------------
   // always @(*)
   //   begin
   //      sum <= add_result;
   //  end
   wire [18:0] sm_mant = sm[18:0];
   wire [18:0] gr_mant = {1'b1,gr[`MANT]};
   
endmodule

prac/FpAdd_tb.v
module FpAdd_tb;
   reg [26:0] tst_in1;
   reg [26:0] tst_in2;
   reg        tst_clk;
   reg        tst_rst;
   wire [26:0] tst_out;
   reg [31:0]  fh;
   reg [31:0]  oh;
   reg [31:0]  file_result;
   integer     count;
   integer     total;
   
   reg [26:0]  vec1 [1023:0];
   reg [26:0]  vec2 [1023:0];
   
   initial
     begin
        fh = $fopen("/home/omkar/projects/grav_sim/test/Fp_Add_tstvec.txt","r");
        //oh = $fopen("../run/FpAddtemp.txt","w");
     end

   
   FpAdd dut (
              .clk(tst_clk),
              .rst(tst_rst),
              .in1(tst_in1),
              .in2(tst_in2),
              .sum(tst_out)
              );
   
   always
     begin
        tst_clk <= 1'b1;
        #5;
        tst_clk <= 1'b0;
        #5;
     end
   
   always @(posedge tst_clk)
     begin
        if (tst_rst == 'b1)
          begin
             tst_in1 <= vec1[count];
             tst_in2 <= vec2[count];
             $display("%b",tst_out);
             count <= count + 1;
             if (count == total)
               begin
                  $finish;
               end
          end
     end
   


   
   initial
     begin
        $dumpvars;
        count = 0;
        while (!$feof(fh))
          begin
             file_result = $fscanf(fh,"%b %b",vec1[count],vec2[count]);
             count = count + 1;
          end
        total <= count;
        count <= 0;
        tst_rst = 'b0;
        repeat (5)
          begin
             @ (posedge tst_clk);
          end
        //#50;
        tst_rst <= 'b1;
        
        #1000;
        $finish;
        
        
     end

endmodule

run/dump.vcd
$date
	Wed Oct 25 01:35:43 2023
$end
$version
	Icarus Verilog
$end
$timescale
	1s
$end
$scope module FpAdd_tb $end
$var wire 27 ! tst_out [26:0] $end
$var reg 32 " fh [31:0] $end
$var reg 32 # file_result [31:0] $end
$var reg 1 $ tst_clk $end
$var reg 27 % tst_in1 [26:0] $end
$var reg 27 & tst_in2 [26:0] $end
$var reg 1 ' tst_rst $end
$var integer 32 ( count [31:0] $end
$var integer 32 ) total [31:0] $end
$scope module dut $end
$var wire 1 $ clk $end
$var wire 27 * in1 [26:0] $end
$var wire 27 + in2 [26:0] $end
$var wire 1 ' rst $end
$var wire 1 , sub $end
$var wire 8 - small_shift [25:18] $end
$var wire 19 . sm_mant [18:0] $end
$var wire 19 / gr_mant [18:0] $end
$var wire 18 0 final_add [17:0] $end
$var reg 20 1 add_out [19:0] $end
$var reg 27 2 add_result [26:0] $end
$var reg 8 3 expt_carry [25:18] $end
$var reg 18 4 final_sub [17:0] $end
$var reg 27 5 gr [26:0] $end
$var reg 27 6 greater [26:0] $end
$var reg 8 7 net_expt [25:18] $end
$var reg 19 8 net_small [18:0] $end
$var reg 20 9 sm [19:0] $end
$var reg 8 : sm_shift [25:18] $end
$var reg 27 ; smaller [26:0] $end
$var reg 8 < sub_expt [7:0] $end
$var reg 19 = sub_out [18:0] $end
$var reg 27 > sub_result [26:0] $end
$var reg 5 ? sub_shift [4:0] $end
$var reg 27 @ sum [26:0] $end
$var reg 19 A temp_sub [18:0] $end
$upscope $end
$upscope $end
$enddefinitions $end
#0
$dumpvars
b1000000000000000000 A
b0 @
b0 ?
b0 >
b1000000000000000000 =
b0 <
bx ;
b0 :
b0 9
bx 8
b0 7
bx 6
b0 5
b0 4
b0 3
b0 2
b1000000000000000000 1
b0 0
b1000000000000000000 /
b0 .
bx -
0,
bx +
bx *
b1111101001 )
b0 (
0'
bx &
bx %
1$
b0 #
b10000000000000000000000000000011 "
b0 !
$end
#5
0$
#10
1$
#15
0$
#20
1$
#25
0$
#30
1$
#35
0$
#40
1'
1$
#45
0$
#50
bx 4
bx A
bx !
bx @
b0 8
bx 0
b110011 -
bx <
bx 3
bx >
bx 1
bx =
bx 2
b101100110000010001001110111 ;
b110011001010011000000001001 6
x,
bx .
b1xxxxxxxxxxxxxxxxxx /
bx :
bx 7
bx 9
bx 5
b1 (
b110011001010011000000001001 &
b110011001010011000000001001 +
b101100110000010001001110111 %
b101100110000010001001110111 *
1$
#55
0$
#60
b10011000000001001 4
b1 8
b1010011000000001001 A
b10011001 3
b110011001010011000000001001 !
b110011001010011000000001001 @
b10011000000001001 0
b10010 -
b10011001 <
b110011001010011000000001001 >
b1010011000000001001 =
b1010011000000001001 1
b110011001010011000000001001 2
b1001011110111010011011110 ;
b1011101000110101010100100 6
0,
b0 .
b1010011000000001001 /
b110011 :
b10011001 7
b10000000000000000000 9
b110011001010011000000001001 5
b10 (
b1001011110111010011011110 &
b1001011110111010011011110 +
b1011101000110101010100100 %
b1011101000110101010100100 *
1$
#65
0$
#70
b110101010100011 4
b1000110101010100011 A
b1011101000110101010100101 !
b1011101000110101010100101 @
b0 8
b110101010100101 0
b1100100 -
b1011101 <
b1011101 3
b1011101000110101010100011 >
b1000110101010100101 1
b1000110101010100011 =
b1011101000110101010100101 2
b100111110011100001011111110 ;
b10100010101010111101001110 6
b1 .
b1000110101010100100 /
b10010 :
b1011101 7
b1 9
b1011101000110101010100100 5
b11 (
b100111110011100001011111110 &
b100111110011100001011111110 +
b10100010101010111101001110 %
b10100010101010111101001110 *
1$
#75
0$
#80
b101010111101001110 4
b10100010101010111101001110 >
b10100010101010111101001110 2
b1101010111101001110 A
b101010111101001110 0
b11110 -
b10100010101010111101001110 !
b10100010101010111101001110 @
b10100010 <
b10100010 3
b1101010111101001110 =
b1101010111101001110 1
b10000100010001110100111011 ;
b10100010011111001110011111 6
1,
b0 .
b1101010111101001110 /
b1100100 :
b10100010 7
b10000000000000000000 9
b10100010101010111101001110 5
b100 (
b10000100010001110100111011 &
b10000100010001110100111011 +
b10100010011111001110011111 %
b10100010011111001110011111 *
1$
#85
0$
#90
b10100010011111001110011111 >
b10100010011111001110011111 !
b10100010011111001110011111 @
b11111001110011111 4
b10100010011111001110011111 2
b1011111001110011111 A
b11111001110011111 0
b10000011 -
b1011111001110011111 1
b1011111001110011111 =
b100110100111110101010110100 ;
b110110111110101000010100101 6
0,
b1011111001110011111 /
b11110 :
b0 9
b10100010011111001110011111 5
b101 (
b100110100111110101010110100 &
b100110100111110101010110100 +
b110110111110101000010100101 %
b110110111110101000010100101 *
1$
#95
0$
#100
b110101000010100101 4
b1110101000010100101 A
b110110111110101000010100101 !
b110110111110101000010100101 @
b110101000010100101 0
b10101001 -
b10110111 <
b10110111 3
b110110111110101000010100101 >
b1110101000010100101 =
b1110101000010100101 1
b110110111110101000010100101 2
b101100010001100001110001 ;
b111010101010100010011111100 6
b1110101000010100101 /
b10000011 :
b10110111 7
b10000000000000000000 9
b110110111110101000010100101 5
b110 (
b111010101010100010011111100 &
b111010101010100010011111100 +
b101100010001100001110001 %
b101100010001100001110001 *
1$
#105
0$
#110
b111010101010100010011111100 !
b111010101010100010011111100 @
b10100010011111100 4
b111010101010100010011111100 >
b111010101010100010011111100 2
b1010100010011111100 A
b10100010011111100 0
b101101 -
b11010101 <
b11010101 3
b1010100010011111100 1
b1010100010011111100 =
b110011001100101100110001010 ;
b11000110010010000001001000 6
1,
b1010100010011111100 /
b10101001 :
b11010101 7
b0 9
b111010101010100010011111100 5
b111 (
b11000110010010000001001000 &
b11000110010010000001001000 +
b110011001100101100110001010 %
b110011001100101100110001010 *
1$
#115
0$
#120
b10010000001001000 4
b1010010000001001000 A
b11000110010010000001001000 !
b11000110010010000001001000 @
b10010000001001000 0
b10001010 -
b11000110 <
b11000110 3
b11000110010010000001001000 >
b1010010000001001000 =
b1010010000001001000 1
b11000110010010000001001000 2
b100000110101101110011011101 ;
b10010000011001101111010110 6
b1010010000001001000 /
b101101 :
b11000110 7
b10000000000000000000 9
b11000110010010000001001000 5
b1000 (
b100000110101101110011011101 &
b100000110101101110011011101 +
b10010000011001101111010110 %
b10010000011001101111010110 *
1$
#125
0$
#130
b10010000011001101111010110 !
b10010000011001101111010110 @
b11001101111010110 4
b10 8
b10010000011001101111010110 >
b10010000011001101111010110 2
b1011001101111010110 A
b11001101111010110 0
b10001 -
b10010000 <
b10010000 3
b1011001101111010110 1
b1011001101111010110 =
b10101010000000100111010011 ;
b110111011011101111111000110 6
b1011001101111010110 /
b10001010 :
b10010000 7
b10010000011001101111010110 5
b1001 (
b10101010000000100111010011 &
b10101010000000100111010011 +
b110111011011101111111000110 %
b110111011011101111111000110 *
1$
#135
0$
#140
b11101111111000100 4
b1011101111111000100 A
b110111011011101111111000100 !
b110111011011101111111000100 @
b0 8
b11101111111001000 0
b101001 -
b10111011 <
b10111011 3
b110111011011101111111000100 >
b1011101111111000100 =
b1011101111111001000 1
b110111011011101111111001000 2
b1110101000011101101001000 ;
b110011110000011110010100001 6
b10 .
b1011101111111000110 /
b10001 :
b10111011 7
b10 9
b110111011011101111111000110 5
b1010 (
b110011110000011110010100001 &
b110011110000011110010100001 +
b1110101000011101101001000 %
b1110101000011101101001000 *
1$
#145
0$
#150
b110011110000011110010100001 !
b110011110000011110010100001 @
b11110010100001 4
b110011110000011110010100001 >
b110011110000011110010100001 2
b1000011110010100001 A
b11110010100001 0
b10000111 -
b10011110 <
b10011110 3
b1000011110010100001 1
b1000011110010100001 =
b101000010000011101001001010 ;
b11001001010001101110100010 6
b0 .
b1000011110010100001 /
b101001 :
b10011110 7
b0 9
b110011110000011110010100001 5
b1011 (
b101000010000011101001001010 &
b101000010000011101001001010 +
b11001001010001101110100010 %
b11001001010001101110100010 *
1$
#155
0$
#160
b10001101110100010 4
b1010001101110100010 A
b11001001010001101110100010 !
b11001001010001101110100010 @
b10001101110100010 0
b1001110 -
b11001001 <
b11001001 3
b11001001010001101110100010 >
b1010001101110100010 =
b1010001101110100010 1
b11001001010001101110100010 2
b101101101011100100110011100 ;
b10111011100001001110000111 6
b1010001101110100010 /
b10000111 :
b11001001 7
b10000000000000000000 9
b11001001010001101110100010 5
b1100 (
b10111011100001001110000111 &
b10111011100001001110000111 +
b101101101011100100110011100 %
b101101101011100100110011100 *
1$
#165
0$
#170
b10111011100001001110000111 !
b10111011100001001110000111 @
b100001001110000111 4
b10111011100001001110000111 >
b10111011100001001110000111 2
b1100001001110000111 A
b100001001110000111 0
b110110 -
b10111011 <
b10111011 3
b1100001001110000111 1
b1100001001110000111 =
b101010111111001010010000010 ;
b10001101111111110110001000 6
b1100001001110000111 /
b1001110 :
b10111011 7
b10111011100001001110000111 5
b1101 (
b10001101111111110110001000 &
b10001101111111110110001000 +
b101010111111001010010000010 %
b101010111111001010010000010 *
1$
#175
0$
#180
b10001101111111110110001000 !
b10001101111111110110001000 @
b111111110110001000 4
b11111001110100 8
b10001101111111110110001000 >
b10001101111111110110001000 2
b1111111110110001000 A
b111111110110001000 0
b101 -
b10001101 <
b10001101 3
b1111111110110001000 =
b1111111110110001000 1
b101110110111100111010000010 ;
b101111011001111010010011100 6
b1111111110110001000 /
b110110 :
b10001101 7
b10001101111111110110001000 5
b1110 (
b101111011001111010010011100 &
b101111011001111010010011100 +
b101110110111100111010000010 %
b101110110111100111010000010 *
1$
#185
0$
#190
b1011011000101000 4
b1001011011000101000 A
b101111011010011001100010000 !
b101111011010011001100010000 @
b0 8
b10011001100010000 0
b11010111 -
b1111011 <
b1111011 3
b101111011001011011000101000 >
b1010011001100010000 1
b1001011011000101000 =
b101111011010011001100010000 2
b100010100010111111011101100 ;
b11101011001001101101010011 6
0,
b11111001110100 .
b1001111010010011100 /
b101 :
b1111011 7
b10000011111001110100 9
b101111011001111010010011100 5
b1111 (
b11101011001001101101010011 &
b11101011001001101101010011 +
b100010100010111111011101100 %
b100010100010111111011101100 *
1$
#195
0$
#200
b1001101101010011 4
b1001001101101010011 A
b1001101101010011 0
b1111111 -
b11101011001001101101010011 !
b11101011001001101101010011 @
b11101011 <
b11101011 3
b11101011001001101101010011 >
b1001001101101010011 =
b1001001101101010011 1
b11101011001001101101010011 2
b111000010101100111101100 ;
b10110111000110111000011101 6
1,
b0 .
b1001001101101010011 /
b11010111 :
b11101011 7
b10000000000000000000 9
b11101011001001101101010011 5
b10000 (
b10110111000110111000011101 &
b10110111000110111000011101 +
b111000010101100111101100 %
b111000010101100111101100 *
1$
#205
0$
#210
b10110111000110111000011101 !
b10110111000110111000011101 @
b110111000011101 4
b1110101101001 8
b10110111000110111000011101 >
b10110111000110111000011101 2
b1000110111000011101 A
b110111000011101 0
b110 -
b10110111 <
b10110111 3
b1000110111000011101 1
b1000110111000011101 =
b11000110101101001000111 ;
b11110010110110010011010 6
0,
b1000110111000011101 /
b1111111 :
b10110111 7
b0 9
b10110111000110111000011101 5
b10001 (
b11110010110110010011010 &
b11110010110110010011010 +
b11000110101101001000111 %
b11000110101101001000111 *
1$
#215
0$
#220
b11110011000101000000011 !
b11110011000101000000011 @
b10100111100110001 4
b11110010100111100110001 >
b11110011000101000000011 2
b1010100111100110001 A
b0 8
b11000101000000011 0
b10010110 -
b11110 <
b11110 3
b1010100111100110001 =
b1011000101000000011 1
b1001101100000110111100101 ;
b111100011100011110100001000 6
b1110101101001 .
b1010110110010011010 /
b110 :
b11110 7
b1110101101001 9
b11110010110110010011010 5
b10010 (
b111100011100011110100001000 &
b111100011100011110100001000 +
b1001101100000110111100101 %
b1001101100000110111100101 *
1$
#225
0$
#230
b100011110100001000 4
b1100011110100001000 A
b100011110100001000 0
b110101 -
b111100011100011110100001000 !
b111100011100011110100001000 @
b11100011 <
b11100011 3
b111100011100011110100001000 >
b1100011110100001000 1
b1100011110100001000 =
b111100011100011110100001000 2
b100110010000000111001111101 ;
b1100111010000100101100001 6
1,
b0 .
b1100011110100001000 /
b10010110 :
b11100011 7
b0 9
b111100011100011110100001000 5
b10011 (
b1100111010000100101100001 &
b1100111010000100101100001 +
b100110010000000111001111101 %
b100110010000000111001111101 *
1$
#235
0$
#240
b10000100101100001 4
b1010000100101100001 A
b1100111010000100101100001 !
b1100111010000100101100001 @
b10000100101100001 0
b100101 -
b1100111 <
b1100111 3
b1100111010000100101100001 >
b1010000100101100001 =
b1010000100101100001 1
b1100111010000100101100001 2
b11010011010111111000100101 ;
b111111000100001101100111010 6
b1010000100101100001 /
b110101 :
b1100111 7
b10000000000000000000 9
b1100111010000100101100001 5
b10100 (
b11010011010111111000100101 &
b11010011010111111000100101 +
b111111000100001101100111010 %
b111111000100001101100111010 *
1$
#245
0$
#250
b100001101100111010 4
b1100001101100111010 A
b111111000100001101100111010 !
b111111000100001101100111010 @
b100001101100111010 0
b1001000 -
b11111000 <
b11111000 3
b111111000100001101100111010 >
b1100001101100111010 1
b1100001101100111010 =
b111111000100001101100111010 2
b1111101000110110111111111 ;
b11000101101011010111100000 6
b1100001101100111010 /
b100101 :
b11111000 7
b0 9
b111111000100001101100111010 5
b10101 (
b11000101101011010111100000 &
b11000101101011010111100000 +
b1111101000110110111111111 %
b1111101000110110111111111 *
1$
#255
0$
#260
b101011010111100000 4
b1 8
b1101011010111100000 A
b11000101101011010111100000 !
b11000101101011010111100000 @
b101011010111100000 0
b10010 -
b11000101 <
b11000101 3
b11000101101011010111100000 >
b1101011010111100000 =
b1101011010111100000 1
b11000101101011010111100000 2
b1010111000010011010110001 ;
b101101001100000101101000101 6
0,
b1101011010111100000 /
b1001000 :
b11000101 7
b11000101101011010111100000 5
b10110 (
b101101001100000101101000101 &
b101101001100000101101000101 +
b1010111000010011010110001 %
b1010111000010011010110001 *
1$
#265
0$
#270
b100000101101000100 4
b1100000101101000100 A
b101101001100000101101000100 !
b101101001100000101101000100 @
b0 8
b100000101101000110 0
b1110001 -
b1101001 <
b1101001 3
b101101001100000101101000100 >
b1100000101101000110 1
b1100000101101000100 =
b101101001100000101101000110 2
b101010100001011111011000010 ;
b111000101011000111000111111 6
1,
b1 .
b1100000101101000101 /
b10010 :
b1101001 7
b1 9
b101101001100000101101000101 5
b10111 (
b101010100001011111011000010 &
b101010100001011111011000010 +
b111000101011000111000111111 %
b111000101011000111000111111 *
1$
#275
0$
#280
b11000111000111111 4
b111000101011000111000111111 >
b111000101011000111000111111 2
b1011000111000111111 A
b11000111000111111 0
b1100111 -
b111000101011000111000111111 !
b111000101011000111000111111 @
b11000101 <
b11000101 3
b1011000111000111111 =
b1011000111000111111 1
b101011101101110110001100001 ;
b11000100111110000011010101 6
0,
b0 .
b1011000111000111111 /
b1110001 :
b11000101 7
b10000000000000000000 9
b111000101011000111000111111 5
b11000 (
b101011101101110110001100001 &
b101011101101110110001100001 +
b11000100111110000011010101 %
b11000100111110000011010101 *
1$
#285
0$
#290
b111110000011010101 4
b111 8
b1111110000011010101 A
b11000100111110000011010101 !
b11000100111110000011010101 @
b111110000011010101 0
b10000 -
b11000100 <
b11000100 3
b11000100111110000011010101 >
b1111110000011010101 1
b1111110000011010101 =
b11000100111110000011010101 2
b1001001110011110110001101 ;
b101011001000010110001111101 6
1,
b1111110000011010101 /
b1100111 :
b11000100 7
b11000100111110000011010101 5
b11001 (
b1001001110011110110001101 &
b1001001110011110110001101 +
b101011001000010110001111101 %
b101011001000010110001111101 *
1$
#295
0$
#300
b10110001110110 4
b1000010110001110110 A
b101011001000010110001110110 !
b101011001000010110001110110 @
b0 8
b10110010000100 0
b10000110 -
b1011001 <
b1011001 3
b101011001000010110001110110 >
b1000010110001110110 =
b1000010110010000100 1
b101011001000010110010000100 2
b1101111001101011101000000 ;
b111110101011000011101100000 6
b111 .
b1000010110001111101 /
b10000 :
b1011001 7
b111 9
b101011001000010110001111101 5
b11010 (
b111110101011000011101100000 &
b111110101011000011101100000 +
b1101111001101011101000000 %
b1101111001101011101000000 *
1$
#305
0$
#310
b111110101011000011101100000 !
b111110101011000011101100000 @
b11000011101100000 4
b111110101011000011101100000 >
b111110101011000011101100000 2
b1011000011101100000 A
b11000011101100000 0
b10100000 -
b11110101 <
b11110101 3
b1011000011101100000 1
b1011000011101100000 =
b1101010001011000110111 ;
b10101101100010010111011001 6
b0 .
b1011000011101100000 /
b10000110 :
b11110101 7
b0 9
b111110101011000011101100000 5
b11011 (
b1101010001011000110111 &
b1101010001011000110111 +
b10101101100010010111011001 %
b10101101100010010111011001 *
1$
#315
0$
#320
b100010010111011001 4
b1100010010111011001 A
b10101101100010010111011001 !
b10101101100010010111011001 @
b100010010111011001 0
b100001 -
b10101101 <
b10101101 3
b10101101100010010111011001 >
b1100010010111011001 =
b1100010010111011001 1
b10101101100010010111011001 2
b110010010011001000111111101 ;
b110110011100011100000110101 6
0,
b1100010010111011001 /
b10100000 :
b10101101 7
b10101101100010010111011001 5
b11100 (
b110110011100011100000110101 &
b110110011100011100000110101 +
b110010010011001000111111101 %
b110010010011001000111111101 *
1$
#325
0$
#330
b100011100000110101 4
b1100011100000110101 A
b110110011100011100000110101 !
b110110011100011100000110101 @
b100011100000110101 0
b1110111 -
b10110011 <
b10110011 3
b110110011100011100000110101 >
b1100011100000110101 1
b1100011100000110101 =
b110110011100011100000110101 2
b11010001001100010100010 ;
b10010001101100101110000010 6
b1100011100000110101 /
b100001 :
b10110011 7
b10000000000000000000 9
b110110011100011100000110101 5
b11101 (
b10010001101100101110000010 &
b10010001101100101110000010 +
b11010001001100010100010 %
b11010001001100010100010 *
1$
#335
0$
#340
b101100101110000010 4
b1101100101110000010 A
b10010001101100101110000010 !
b10010001101100101110000010 @
b101100101110000010 0
b11000000 -
b10010001 <
b10010001 3
b10010001101100101110000010 >
b1101100101110000010 =
b1101100101110000010 1
b10010001101100101110000010 2
b100111111011011001110101001 ;
b11111111000010000100010011 6
b1101100101110000010 /
b1110111 :
b10010001 7
b0 9
b10010001101100101110000010 5
b11110 (
b11111111000010000100010011 &
b11111111000010000100010011 +
b100111111011011001110101001 %
b100111111011011001110101001 *
1$
#345
0$
#350
b11111111000010000100010011 !
b11111111000010000100010011 @
b10000100010011 4
b11111111000010000100010011 >
b11111111000010000100010011 2
b1000010000100010011 A
b10000100010011 0
b10010100 -
b11111111 <
b11111111 3
b1000010000100010011 1
b1000010000100010011 =
b100001111001101110001001110 ;
b110100011011010001001010100 6
1,
b1000010000100010011 /
b11000000 :
b11111111 7
b10000000000000000000 9
b11111111000010000100010011 5
b11111 (
b110100011011010001001010100 &
b110100011011010001001010100 +
b100001111001101110001001110 %
b100001111001101110001001110 *
1$
#355
0$
#360
b11010001001010100 4
b1011010001001010100 A
b110100011011010001001010100 !
b110100011011010001001010100 @
b11010001001010100 0
b11100 -
b10100011 <
b10100011 3
b110100011011010001001010100 >
b1011010001001010100 =
b1011010001001010100 1
b110100011011010001001010100 2
b11001110101101111000000000 ;
b111101010000110000101010010 6
0,
b1011010001001010100 /
b10010100 :
b10100011 7
b110100011011010001001010100 5
b100000 (
b11001110101101111000000000 &
b11001110101101111000000000 +
b111101010000110000101010010 %
b111101010000110000101010010 *
1$
#365
0$
#370
b111101010000110000101010010 !
b111101010000110000101010010 @
b110000101010010 4
b111101010000110000101010010 >
b111101010000110000101010010 2
b1000110000101010010 A
b110000101010010 0
b10010000 -
b11101010 <
b11101010 3
b1000110000101010010 1
b1000110000101010010 =
b100010011000111101011001000 ;
b10100011011101110100000001 6
1,
b1000110000101010010 /
b11100 :
b11101010 7
b0 9
b111101010000110000101010010 5
b100001 (
b100010011000111101011001000 &
b100010011000111101011001000 +
b10100011011101110100000001 %
b10100011011101110100000001 *
1$
#375
0$
#380
b11101110100000001 4
b1011101110100000001 A
b10100011011101110100000001 !
b10100011011101110100000001 @
b11101110100000001 0
b10100000 -
b10100011 <
b10100011 3
b10100011011101110100000001 >
b1011101110100000001 =
b1011101110100000001 1
b10100011011101110100000001 2
b1011100100110000010101011 ;
b111111100110011010000101010 6
b1011101110100000001 /
b10010000 :
b10100011 7
b10000000000000000000 9
b10100011011101110100000001 5
b100010 (
b1011100100110000010101011 &
b1011100100110000010101011 +
b111111100110011010000101010 %
b111111100110011010000101010 *
1$
#385
0$
#390
b110011010000101010 4
b1110011010000101010 A
b111111100110011010000101010 !
b111111100110011010000101010 @
b110011010000101010 0
b1011001 -
b11111100 <
b11111100 3
b111111100110011010000101010 >
b1110011010000101010 1
b1110011010000101010 =
b111111100110011010000101010 2
b101011001011111001011001000 ;
b110110010101101010111010010 6
b1110011010000101010 /
b10100000 :
b11111100 7
b0 9
b111111100110011010000101010 5
b100011 (
b101011001011111001011001000 &
b101011001011111001011001000 +
b110110010101101010111010010 %
b110110010101101010111010010 *
1$
#395
0$
#400
b110110010101101010111010010 !
b110110010101101010111010010 @
b101101010111010010 4
b110110010101101010111010010 >
b110110010101101010111010010 2
b1101101010111010010 A
b101101010111010010 0
b10100 -
b10110010 <
b10110010 3
b1101101010111010010 =
b1101101010111010010 1
b100001111000111011001100000 ;
b100100011100010011000011000 6
0,
b1101101010111010010 /
b1011001 :
b10110010 7
b10000000000000000000 9
b110110010101101010111010010 5
b100100 (
b100001111000111011001100000 &
b100001111000111011001100000 +
b100100011100010011000011000 %
b100100011100010011000011000 *
1$
#405
0$
#410
b100100011100010011000011000 !
b100100011100010011000011000 @
b100010011000011000 4
b100 8
b100100011100010011000011000 >
b100100011100010011000011000 2
b1100010011000011000 A
b100010011000011000 0
b10000 -
b100011 <
b100011 3
b1100010011000011000 1
b1100010011000011000 =
b110101110000110001110001110 ;
b10111110011010111000011011 6
b1100010011000011000 /
b10100 :
b100011 7
b100100011100010011000011000 5
b100101 (
b110101110000110001110001110 &
b110101110000110001110001110 +
b10111110011010111000011011 %
b10111110011010111000011011 *
1$
#415
0$
