rtl/FpAdd.v
//--------------------------------------------------------------------
// Author: Omkar Girish Kamath (201EC140)
// Date: October 1st, 2023
// Module Name: FpAdd
// Module Description: Implements the custom 27-bit floating point
//                     adder where MSB is sign bit, next 8-bits are
//                     exponent in excess 127 and last 18-bits are ma-
//                     ntissa.
//--------------------------------------------------------------------

`define SIGN 26
`define EXP 25:18
`define MANT 17:0


module FpAdd (
              clk,             // replace string with clock
              in1,          // replace string with fp_in1
              in2,          // replace string with fp_in2
              sum,          // replace string with fp_sum
              rst
              );

   //--------------------------------------------------------------------
   // Inputs
   //--------------------------------------------------------------------
   input wire clk;
   input wire [26:0] in1;
   input wire [26:0] in2;
   input wire        rst;
   
   //--------------------------------------------------------------------
   // Outputs
   //--------------------------------------------------------------------
   output reg [26:0] sum;

   //--------------------------------------------------------------------
   // Internals
   //--------------------------------------------------------------------
   parameter sign = 26;
   parameter ex_end = 25;
   parameter ex_st = 18;
   parameter ma_end = 17;
   parameter ma_st = 0;

   //--------------------------------------------------------------------
   // First Stage
   //--------------------------------------------------------------------
   
   //--------------------------------------------------------------------
   // Finding greater number among the 2
   //--------------------------------------------------------------------
   reg [`SIGN:0] greater;
   reg [`SIGN:0] smaller;

   always @(*)
     begin
        if (in1[`EXP] > in2[`EXP])
          begin
             greater <= in1;
             smaller <= in2;
          end
        else
          if (in1[`EXP] == in2[`EXP] && in1[`MANT] > in2[`MANT])
            begin
               greater <= in1;
               smaller <= in2;
            end
          else
            begin
               greater <= in2;
               smaller <= in1;
            end
     end // always @ (*)
   
   
   //--------------------------------------------------------------------
   // Net smaller value for arithmetic
   //--------------------------------------------------------------------
   reg [18:0] net_small;
   wire [`EXP] small_shift;
   
   assign small_shift = greater[`EXP] - smaller[`EXP];
   
   always @(*)
     begin
        if (greater[`EXP] - smaller[`EXP] <= 5'd18)
          begin
             net_small <= {1'b1,smaller[`MANT]} >> (small_shift);
          end
        else
          begin
             net_small <= 'b0;
          end
     end // always @ (*)


   //--------------------------------------------------------------------
   // Pipeline Register's
   //--------------------------------------------------------------------
   reg [`SIGN:0] gr;
   reg [19:0] sm;
   reg [`EXP]    net_expt;
   reg [`EXP]    sm_shift;
   
   always @(posedge clk )
     begin
        if (rst == 'b0)
          begin
             gr <= 'b0;
             sm <= 'b0;
             net_expt <= 'b0;
             sm_shift <= 'b0;
          end 
        else
           begin
             gr <= greater;
             sm <= {smaller[`SIGN],net_small}; // check for sm
             net_expt <= greater[`EXP];
             sm_shift <= small_shift;
          end    
     end

   
   //--------------------------------------------------------------------
   // Second Stage
   //--------------------------------------------------------------------
   
   //--------------------------------------------------------------------
   // Deciding Addition or Subtraction
   //--------------------------------------------------------------------
   wire sub;
   assign sub = (gr[`SIGN] ^ sm[19]);
   

   //--------------------------------------------------------------------
   // Addition
   //--------------------------------------------------------------------
   
   //--------------------------------------------------------------------
   // Addition Output
   //--------------------------------------------------------------------
   reg [19:0] add_out;
   
   always @(*)
      begin
         add_out <= ({1'b1,gr[`MANT]} + {sm[18:0]});
      end


   //--------------------------------------------------------------------
   // net exponent adder if carry generated in addition
   //--------------------------------------------------------------------
   reg [`EXP] expt_carry;

   always @(*)
     begin
        expt_carry <= net_expt + {7'b0,add_out[19]};
     end


   //--------------------------------------------------------------------
   // result from the whole flow if sign bits of both numbers are equal
   // i.e addition of their magnitudes
   //--------------------------------------------------------------------
   reg [26:0] add_result;
   
   wire [17:0] final_add = (add_out[19]) ? 
               {add_out[18:1]} : add_out[17:0];
   

   always @(*)
     begin
        add_result <= {gr[`SIGN],expt_carry,final_add};
     end // always @ (*)

   
   //--------------------------------------------------------------------
   // Subtraction
   //--------------------------------------------------------------------
   
   //--------------------------------------------------------------------
   // Subtraction Output
   //--------------------------------------------------------------------
   reg [18:0] sub_out;

   always @(*)
     begin
        sub_out <= {1'b1,gr[`MANT]} - sm[18:0];
     end

   //--------------------------------------------------------------------
   // Exponent Difference after subtraction Generator
   //--------------------------------------------------------------------
   reg [4:0] sub_shift;
      always @(*)
     begin
        casex (sub_out)
          19'b1XXXXXXXXXXXXXXXXXX: sub_shift <= 5'd0;
          19'b01XXXXXXXXXXXXXXXXX: sub_shift <= 5'd1;
          19'b001XXXXXXXXXXXXXXXX: sub_shift <= 5'd2;
          19'b0001XXXXXXXXXXXXXXX: sub_shift <= 5'd3;
          19'b00001XXXXXXXXXXXXXX: sub_shift <= 5'd4;
          19'b000001XXXXXXXXXXXXX: sub_shift <= 5'd5;
          19'b0000001XXXXXXXXXXXX: sub_shift <= 5'd6;
          19'b00000001XXXXXXXXXXX: sub_shift <= 5'd7;
          19'b000000001XXXXXXXXXX: sub_shift <= 5'd8;
          19'b0000000001XXXXXXXXX: sub_shift <= 5'd9;
          19'b00000000001XXXXXXXX: sub_shift <= 5'd10;
          19'b000000000001XXXXXXX: sub_shift <= 5'd11;
          19'b0000000000001XXXXXX: sub_shift <= 5'd12;
          19'b00000000000001XXXXX: sub_shift <= 5'd13;
          19'b000000000000001XXXX: sub_shift <= 5'd14;
          19'b0000000000000001XXX: sub_shift <= 5'd15;
          19'b00000000000000001XX: sub_shift <= 5'd16;
          19'b000000000000000001X: sub_shift <= 5'd17;
          19'b0000000000000000001: sub_shift <= 5'd18;
          19'b0000000000000000000: sub_shift <= 5'd19;
          default:                sub_shift <= 5'd0;
        endcase
     end // always @ (*)

  
   //--------------------------------------------------------------------
   // Calculating net exponent
   //--------------------------------------------------------------------
   reg [7:0] sub_expt;
   
   always @(*)
     begin
        sub_expt <= net_expt - {3'b0,sub_shift};
     end
   

   //--------------------------------------------------------------------
   // Calculating Final Subtraction Out after shift
   //--------------------------------------------------------------------
   reg [17:0] final_sub;
   reg [18:0] temp_sub;
   always @(*)
     begin
        temp_sub <= (sub_out << sub_shift);
        final_sub <= temp_sub[17:0];
     end
   //--------------------------------------------------------------------
   // Calculating Final Subtraction Result
   //--------------------------------------------------------------------
   reg [26:0] sub_result;

   always @(*)
     begin
        sub_result <= {gr[`SIGN],sub_expt,final_sub};
     end

   //--------------------------------------------------------------------
   // Calculating Final Subtraction Result
   //--------------------------------------------------------------------
   always @(*)
     begin
        if (sub)
          begin
             sum <= sub_result;
          end
        else
          begin
             sum <= add_result;
          end
     end

   //--------------------------------------------------------------------
   // Test code (not part of the RTL)
   //--------------------------------------------------------------------
   // always @(*)
   //   begin
   //      sum <= add_result;
   //  end
   wire [18:0] sm_mant = sm[18:0];
   wire [18:0] gr_mant = {1'b1,gr[`MANT]};
   
endmodule

prac/FpAdd_tb.v
module FpAdd_tb;
   reg [26:0] tst_in1;
   reg [26:0] tst_in2;
   reg        tst_clk;
   reg        tst_rst;
   wire [26:0] tst_out;
   reg [31:0]  fh;
   reg [31:0]  oh;
   reg [31:0]  file_result;
   integer     count;
   integer     total;
   
   reg [26:0]  vec1 [1023:0];
   reg [26:0]  vec2 [1023:0];
   
   initial
     begin
        fh = $fopen("/home/omkar/projects/grav_sim/test/Fp_Add_tstvec.txt","r");
        //oh = $fopen("../run/FpAddtemp.txt","w");
     end

   
   FpAdd dut (
              .clk(tst_clk),
              .rst(tst_rst),
              .in1(tst_in1),
              .in2(tst_in2),
              .sum(tst_out)
              );
   
   always
     begin
        tst_clk <= 1'b1;
        #5;
        tst_clk <= 1'b0;
        #5;
     end
   
   always @(posedge tst_clk)
     begin
        if (tst_rst == 'b1)
          begin
             tst_in1 <= vec1[count];
             tst_in2 <= vec2[count];
             $display("%b",tst_out);
             count <= count + 1;
             if (count == total)
               begin
                  $finish;
               end
          end
     end
   


   
   initial
     begin
        $dumpvars;
        count = 0;
        while (!$feof(fh))
          begin
             file_result = $fscanf(fh,"%b %b",vec1[count],vec2[count]);
             count = count + 1;
          end
        total <= count;
        count <= 0;
        tst_rst = 'b0;
        repeat (5)
          begin
             @ (posedge tst_clk);
          end
        //#50;
        tst_rst <= 'b1;
        
        #1000;
        $finish;
        
        
     end

endmodule

run/dump.vcd
$date
	Wed Oct 25 01:16:43 2023
$end
$version
	Icarus Verilog
$end
$timescale
	1s
$end
$scope module FpAdd_tb $end
$var wire 27 ! tst_out [26:0] $end
$var reg 32 " fh [31:0] $end
$var reg 32 # file_result [31:0] $end
$var reg 1 $ tst_clk $end
$var reg 27 % tst_in1 [26:0] $end
$var reg 27 & tst_in2 [26:0] $end
$var reg 1 ' tst_rst $end
$var integer 32 ( count [31:0] $end
$var integer 32 ) total [31:0] $end
$scope module dut $end
$var wire 1 $ clk $end
$var wire 27 * in1 [26:0] $end
$var wire 27 + in2 [26:0] $end
$var wire 1 ' rst $end
$var wire 1 , sub $end
$var wire 8 - small_shift [25:18] $end
$var wire 19 . sm_mant [18:0] $end
$var wire 19 / gr_mant [18:0] $end
$var wire 18 0 final_add [17:0] $end
$var reg 20 1 add_out [19:0] $end
$var reg 27 2 add_result [26:0] $end
$var reg 8 3 expt_carry [25:18] $end
$var reg 18 4 final_sub [17:0] $end
$var reg 27 5 gr [26:0] $end
$var reg 27 6 greater [26:0] $end
$var reg 8 7 net_expt [25:18] $end
$var reg 19 8 net_small [18:0] $end
$var reg 20 9 sm [19:0] $end
$var reg 8 : sm_shift [25:18] $end
$var reg 27 ; smaller [26:0] $end
$var reg 8 < sub_expt [7:0] $end
$var reg 19 = sub_out [18:0] $end
$var reg 27 > sub_result [26:0] $end
$var reg 5 ? sub_shift [4:0] $end
$var reg 27 @ sum [26:0] $end
$var reg 19 A temp_sub [18:0] $end
$upscope $end
$upscope $end
$enddefinitions $end
#0
$dumpvars
b1000000000000000000 A
b0 @
b0 ?
b0 >
b1000000000000000000 =
b0 <
bx ;
b0 :
b0 9
bx 8
b0 7
bx 6
b0 5
b0 4
b0 3
b0 2
b1000000000000000000 1
b0 0
b1000000000000000000 /
b0 .
bx -
0,
bx +
bx *
b1100101 )
b0 (
0'
bx &
bx %
1$
b0 #
b10000000000000000000000000000011 "
b0 !
$end
#5
0$
#10
1$
#15
0$
#20
1$
#25
0$
#30
1$
#35
0$
#40
1'
1$
#45
0$
#50
bx 4
bx A
bx !
bx @
b0 8
bx 0
b11000001 -
bx <
bx 3
bx >
bx 1
bx =
bx 2
b100100110101101001001010000 ;
b11100111011010111011010100 6
x,
bx .
b1xxxxxxxxxxxxxxxxxx /
bx :
bx 7
bx 9
bx 5
b1 (
b100100110101101001001010000 &
b100100110101101001001010000 +
b11100111011010111011010100 %
b11100111011010111011010100 *
1$
#55
0$
#60
b11010111011010100 4
b1011010111011010100 A
b11100111 3
b11100111011010111011010100 !
b11100111011010111011010100 @
b11010111011010100 0
b11000110 -
b11100111 <
b11100111011010111011010100 >
b1011010111011010100 =
b1011010111011010100 1
b11100111011010111011010100 2
b101010010101101001 ;
b11000110100111111100100001 6
1,
b0 .
b1011010111011010100 /
b11000001 :
b11100111 7
b10000000000000000000 9
b11100111011010111011010100 5
b10 (
b11000110100111111100100001 &
b11000110100111111100100001 +
b101010010101101001 %
b101010010101101001 *
1$
#65
0$
#70
b11000110100111111100100001 !
b11000110100111111100100001 @
b100111111100100001 4
b11000110100111111100100001 >
b11000110100111111100100001 2
b1100111111100100001 A
b100111111100100001 0
b10110101 -
b11000110 <
b11000110 3
b1100111111100100001 1
b1100111111100100001 =
b100001100111000001100000001 ;
b11000001011010011110000010 6
0,
b1100111111100100001 /
b11000110 :
b11000110 7
b0 9
b11000110100111111100100001 5
b11 (
b100001100111000001100000001 &
b100001100111000001100000001 +
b11000001011010011110000010 %
b11000001011010011110000010 *
1$
#75
0$
#80
b11000001011010011110000010 !
b11000001011010011110000010 @
b11010011110000010 4
b11000001011010011110000010 >
b11000001011010011110000010 2
b1011010011110000010 A
b11010011110000010 0
b10101101 -
b11000001 <
b11000001 3
b1011010011110000010 =
b1011010011110000010 1
b11100001100001011111 ;
b110110000011110100011011010 6
1,
b1011010011110000010 /
b10110101 :
b11000001 7
b10000000000000000000 9
b11000001011010011110000010 5
b100 (
b110110000011110100011011010 &
b110110000011110100011011010 +
b11100001100001011111 %
b11100001100001011111 *
1$
#85
0$
#90
b11110100011011010 4
b1011110100011011010 A
b110110000011110100011011010 !
b110110000011110100011011010 @
b11110100011011010 0
b101001 -
b10110000 <
b10110000 3
b110110000011110100011011010 >
b1011110100011011010 1
b1011110100011011010 =
b110110000011110100011011010 2
b10110101111111001011010110 ;
b111011110010010111100101011 6
b1011110100011011010 /
b10101101 :
b10110000 7
b0 9
b110110000011110100011011010 5
b101 (
b10110101111111001011010110 &
b10110101111111001011010110 +
b111011110010010111100101011 %
b111011110010010111100101011 *
1$
#95
0$
#100
b111011110010010111100101011 !
b111011110010010111100101011 @
b10010111100101011 4
b111011110010010111100101011 >
b111011110010010111100101011 2
b1010010111100101011 A
b10010111100101011 0
b10111011 -
b11011110 <
b11011110 3
b1010010111100101011 =
b1010010111100101011 1
b100100110010011111110111110 ;
b11100001011010100001101111 6
b1010010111100101011 /
b101001 :
b11011110 7
b111011110010010111100101011 5
b110 (
b100100110010011111110111110 &
b100100110010011111110111110 +
b11100001011010100001101111 %
b11100001011010100001101111 *
1$
#105
0$
#110
b11010100001101111 4
b1011010100001101111 A
b11100001011010100001101111 !
b11100001011010100001101111 @
b11010100001101111 0
b10101 -
b11100001 <
b11100001 3
b11100001011010100001101111 >
b1011010100001101111 1
b1011010100001101111 =
b11100001011010100001101111 2
b11001111011000110010100 ;
b100101110011110011110011110 6
b1011010100001101111 /
b10111011 :
b11100001 7
b10000000000000000000 9
b11100001011010100001101111 5
b111 (
b100101110011110011110011110 &
b100101110011110011110011110 +
b11001111011000110010100 %
b11001111011000110010100 *
1$
#115
0$
#120
b11110011110011110 4
b1011110011110011110 A
b100101110011110011110011110 !
b100101110011110011110011110 @
b11110011110011110 0
b100111 -
b101110 <
b101110 3
b100101110011110011110011110 >
b1011110011110011110 =
b1011110011110011110 1
b100101110011110011110011110 2
b100111101111000101011001111 ;
b101100100100101011010101111 6
b1011110011110011110 /
b10101 :
b101110 7
b0 9
b100101110011110011110011110 5
b1000 (
b100111101111000101011001111 &
b100111101111000101011001111 +
b101100100100101011010101111 %
b101100100100101011010101111 *
1$
#125
0$
#130
b101100100100101011010101111 !
b101100100100101011010101111 @
b100101011010101111 4
b101100100100101011010101111 >
b101100100100101011010101111 2
b1100101011010101111 A
b100101011010101111 0
b101110 -
b1100100 <
b1100100 3
b1100101011010101111 1
b1100101011010101111 =
b101000001001011111001000010 ;
b1101111000010011101000110 6
0,
b1100101011010101111 /
b100111 :
b1100100 7
b10000000000000000000 9
b101100100100101011010101111 5
b1001 (
b1101111000010011101000110 &
b1101111000010011101000110 +
b101000001001011111001000010 %
b101000001001011111001000010 *
1$
#135
0$
#140
b10011101000110 4
b1000010011101000110 A
b1101111000010011101000110 !
b1101111000010011101000110 @
b10011101000110 0
b10001100 -
b1101111 <
b1101111 3
b1101111000010011101000110 >
b1000010011101000110 =
b1000010011101000110 1
b1101111000010011101000110 2
b1011001100101101111000111 ;
b11100101000111111011001010 6
1,
b1000010011101000110 /
b101110 :
b1101111 7
b1101111000010011101000110 5
b1010 (
b11100101000111111011001010 &
b11100101000111111011001010 +
b1011001100101101111000111 %
b1011001100101101111000111 *
1$
#145
0$
#150
b11100101000111111011001010 !
b11100101000111111011001010 @
b111111011001010 4
b11100101000111111011001010 >
b11100101000111111011001010 2
b1000111111011001010 A
b111111011001010 0
b1011100 -
b11100101 <
b11100101 3
b1000111111011001010 1
b1000111111011001010 =
b101001111110010101011001000 ;
b10101011100110000011010101 6
0,
b1000111111011001010 /
b10001100 :
b11100101 7
b0 9
b11100101000111111011001010 5
b1011 (
b10101011100110000011010101 &
b10101011100110000011010101 +
b101001111110010101011001000 %
b101001111110010101011001000 *
1$
#155
0$
#160
b10101011100110000011010101 !
b10101011100110000011010101 @
b100110000011010101 4
b10101011100110000011010101 >
b10101011100110000011010101 2
b1100110000011010101 A
b100110000011010101 0
b10100000 -
b10101011 <
b10101011 3
b1100110000011010101 =
b1100110000011010101 1
b100101110110101000010111111 ;
b111001110010111011000101001 6
1,
b1100110000011010101 /
b1011100 :
b10101011 7
b10000000000000000000 9
b10101011100110000011010101 5
b1100 (
b111001110010111011000101001 &
b111001110010111011000101001 +
b100101110110101000010111111 %
b100101110110101000010111111 *
1$
#165
0$
#170
b10111011000101001 4
b1010111011000101001 A
b111001110010111011000101001 !
b111001110010111011000101001 @
b10111011000101001 0
b1010110 -
b11001110 <
b11001110 3
b111001110010111011000101001 >
b1010111011000101001 1
b1010111011000101001 =
b111001110010111011000101001 2
b110100001110010110001010000 ;
b111110111010111110000110110 6
0,
b1010111011000101001 /
b10100000 :
b11001110 7
b111001110010111011000101001 5
b1101 (
b111110111010111110000110110 &
b111110111010111110000110110 +
b110100001110010110001010000 %
b110100001110010110001010000 *
1$
#175
0$
#180
b111110111010111110000110110 !
b111110111010111110000110110 @
b10111110000110110 4
b111110111010111110000110110 >
b111110111010111110000110110 2
b1010111110000110110 A
b10111110000110110 0
b10100011 -
b11110111 <
b11110111 3
b1010111110000110110 =
b1010111110000110110 1
b1111010100011010010110 ;
b110110010000111011010011111 6
b1010111110000110110 /
b1010110 :
b11110111 7
b111110111010111110000110110 5
b1110 (
b1111010100011010010110 &
b1111010100011010010110 +
b110110010000111011010011111 %
b110110010000111011010011111 *
1$
#185
0$
#190
b110110010000111011010011111 !
b110110010000111011010011111 @
b111011010011111 4
b110111101111 8
b110110010000111011010011111 >
b110110010000111011010011111 2
b1000111011010011111 A
b111011010011111 0
b111 -
b10110010 <
b10110010 3
b1000111011010011111 1
b1000111011010011111 =
b101111100101111011110111110 ;
b110000011100100000111001000 6
1,
b1000111011010011111 /
b10100011 :
b10110010 7
b0 9
b110110010000111011010011111 5
b1111 (
b101111100101111011110111110 &
b101111100101111011110111110 +
b110000011100100000111001000 %
b110000011100100000111001000 *
1$
#195
0$
#200
b110000011100100111110110111 !
b110000011100100111110110111 @
b100011001111011001 4
b110000011100011001111011001 >
b110000011100100111110110111 2
b1100011001111011001 A
b0 8
b100100111110110111 0
b10011000 -
b10000011 <
b10000011 3
b1100011001111011001 =
b1100100111110110111 1
b111010100111111001000001 ;
b11010010011100111010001001 6
0,
b110111101111 .
b1100100000111001000 /
b111 :
b10000011 7
b10000000110111101111 9
b110000011100100000111001000 5
b10000 (
b11010010011100111010001001 &
b11010010011100111010001001 +
b111010100111111001000001 %
b111010100111111001000001 *
1$
#205
0$
#210
b11100111010001001 4
b1011100111010001001 A
b11010010011100111010001001 !
b11010010011100111010001001 @
b11100111010001001 0
b11010011 -
b11010010 <
b11010010 3
b11010010011100111010001001 >
b1011100111010001001 1
b1011100111010001001 =
b11010010011100111010001001 2
b100000111001000110110011001 ;
b11011010001011000111000101 6
b0 .
b1011100111010001001 /
b10011000 :
b11010010 7
b0 9
b11010010011100111010001001 5
b10001 (
b11011010001011000111000101 &
b11011010001011000111000101 +
b100000111001000110110011001 %
b100000111001000110110011001 *
1$
#215
0$
#220
b11011010001011000111000101 !
b11011010001011000111000101 @
b1011000111000101 4
b11011010001011000111000101 >
b11011010001011000111000101 2
b1001011000111000101 A
b1011000111000101 0
b1010011 -
b11011010 <
b11011010 3
b1001011000111000101 =
b1001011000111000101 1
b110000010010110111000000101 ;
b11010101110111100101100010 6
1,
b1001011000111000101 /
b11010011 :
b11011010 7
b10000000000000000000 9
b11011010001011000111000101 5
b10010 (
b11010101110111100101100010 &
b11010101110111100101100010 +
b110000010010110111000000101 %
b110000010010110111000000101 *
1$
#225
0$
#230
b11010101110111100101100010 !
b11010101110111100101100010 @
b110111100101100010 4
b11010101110111100101100010 >
b11010101110111100101100010 2
b1110111100101100010 A
b110111100101100010 0
b1000111 -
b11010101 <
b11010101 3
b1110111100101100010 1
b1110111100101100010 =
b111011100110101101101001 ;
b110000010011010001101101111 6
b1110111100101100010 /
b1010011 :
b11010101 7
b11010101110111100101100010 5
b10011 (
b110000010011010001101101111 &
b110000010011010001101101111 +
b111011100110101101101001 %
b111011100110101101101001 *
1$
#235
0$
#240
b11010001101101111 4
b1011010001101101111 A
b110000010011010001101101111 !
b110000010011010001101101111 @
b11010001101101111 0
b1011111 -
b10000010 <
b10000010 3
b110000010011010001101101111 >
b1011010001101101111 =
b1011010001101101111 1
b110000010011010001101101111 2
b11000001110011000 ;
b101011111001100100100100000 6
b1011010001101101111 /
b1000111 :
b10000010 7
b0 9
b110000010011010001101101111 5
b10100 (
b101011111001100100100100000 &
b101011111001100100100100000 +
b11000001110011000 %
b11000001110011000 *
1$
#245
0$
#250
b101011111001100100100100000 !
b101011111001100100100100000 @
b1100100100100000 4
b10000 8
b101011111001100100100100000 >
b101011111001100100100100000 2
b1001100100100100000 A
b1100100100100000 0
b1110 -
b1011111 <
b1011111 3
b1001100100100100000 1
b1001100100100100000 =
b100100001000000110011100001 ;
b100101111010000000110111000 6
b1001100100100100000 /
b1011111 :
b1011111 7
b101011111001100100100100000 5
b10101 (
b100100001000000110011100001 &
b100100001000000110011100001 +
b100101111010000000110111000 %
b100101111010000000110111000 *
1$
#255
0$
#260
b100101111010000000111001000 !
b100101111010000000111001000 @
b10000000110101000 4
b100101111010000000110101000 >
b100101111010000000111001000 2
b1010000000110101000 A
b101110000101000000 8
b10000000111001000 0
b1 -
b101111 <
b101111 3
b1010000000110101000 =
b1010000000111001000 1
b110110011011100001010000001 ;
b10110100011100000011001101 6
0,
b10000 .
b1010000000110111000 /
b1110 :
b101111 7
b10000000000000010000 9
b100101111010000000110111000 5
b10110 (
b10110100011100000011001101 &
b10110100011100000011001101 +
b110110011011100001010000001 %
b110110011011100001010000001 *
1$
#265
0$
#270
b11011111100011010 4
b1011011111100011010 A
b1 ?
b0 8
b101000100000110 0
b101010 -
b10110011011011111100011010 !
b10110011011011111100011010 @
b10110011 <
b10110101 3
b10110011011011111100011010 >
b10001010001000001101 1
b101101111110001101 =
b10110101000101000100000110 2
b110001001101001110110101011 ;
b10110011110111000000000110 6
1,
b101110000101000000 .
b1011100000011001101 /
b1 :
b10110100 7
b10101110000101000000 9
b10110100011100000011001101 5
b10111 (
b10110011110111000000000110 &
b10110011110111000000000110 +
b110001001101001110110101011 %
b110001001101001110110101011 *
1$
#275
0$
#280
b10110011110111000000000110 !
b10110011110111000000000110 @
b110111000000000110 4
b10110011110111000000000110 >
b10110011110111000000000110 2
b1110111000000000110 A
b0 ?
b110111000000000110 0
b1101001 -
b10110011 <
b10110011 3
b1110111000000000110 =
b1110111000000000110 1
b11111000110001011011111 ;
b110001000011000011101000010 6
b0 .
b1110111000000000110 /
b101010 :
b10110011 7
b10000000000000000000 9
b10110011110111000000000110 5
b11000 (
b110001000011000011101000010 &
b110001000011000011101000010 +
b11111000110001011011111 %
b11111000110001011011111 *
1$
#285
0$
#290
b11000011101000010 4
b1011000011101000010 A
b110001000011000011101000010 !
b110001000011000011101000010 @
b11000011101000010 0
b10111110 -
b10001000 <
b10001000 3
b110001000011000011101000010 >
b1011000011101000010 1
b1011000011101000010 =
b110001000011000011101000010 2
b100001110011010011001011100 ;
b111001100011001000001101111 6
b1011000011101000010 /
b1101001 :
b10001000 7
b0 9
b110001000011000011101000010 5
b11001 (
b100001110011010011001011100 &
b100001110011010011001011100 +
b111001100011001000001101111 %
b111001100011001000001101111 *
1$
#295
0$
#300
b111001100011001000001101111 !
b111001100011001000001101111 @
b11001000001101111 4
b111001100011001000001101111 >
b111001100011001000001101111 2
b1011001000001101111 A
b11001000001101111 0
b1111110 -
b11001100 <
b11001100 3
b1011001000001101111 =
b1011001000001101111 1
b101111011111011110111111 ;
b110101101011010001100110010 6
0,
b1011001000001101111 /
b10111110 :
b11001100 7
b10000000000000000000 9
b111001100011001000001101111 5
b11010 (
b110101101011010001100110010 &
b110101101011010001100110010 +
b101111011111011110111111 %
b101111011111011110111111 *
1$
#305
0$
#310
b110101101011010001100110010 !
b110101101011010001100110010 @
b11010001100110010 4
b110101101011010001100110010 >
b110101101011010001100110010 2
b1011010001100110010 A
b11010001100110010 0
b11000 -
b10101101 <
b10101101 3
b1011010001100110010 1
b1011010001100110010 =
b100101000110101110010001001 ;
b101000000101001110110010111 6
1,
b1011010001100110010 /
b1111110 :
b10101101 7
b0 9
b110101101011010001100110010 5
b11011 (
b100101000110101110010001001 &
b100101000110101110010001001 +
b101000000101001110110010111 %
b101000000101001110110010111 *
1$
#315
0$
#320
b101000000101001110110010111 !
b101000000101001110110010111 @
b101001110110010111 4
b101000000101001110110010111 >
b101000000101001110110010111 2
b1101001110110010111 A
b101001110110010111 0
b1010011 -
b1000000 <
b1000000 3
b1101001110110010111 =
b1101001110110010111 1
b100110100101111000001011001 ;
b110000111001001111011011111 6
0,
b1101001110110010111 /
b11000 :
b1000000 7
b10000000000000000000 9
b101000000101001110110010111 5
b11100 (
b100110100101111000001011001 &
b100110100101111000001011001 +
b110000111001001111011011111 %
b110000111001001111011011111 *
1$
#325
0$
#330
b110000111001001111011011111 !
b110000111001001111011011111 @
b1001111011011111 4
b110000111001001111011011111 >
b110000111001001111011011111 2
b1001001111011011111 A
b1001111011011111 0
b1100110 -
b10000111 <
b10000111 3
b1001001111011011111 1
b1001001111011011111 =
b1111001111001110010000100 ;
b11011111100100011000110100 6
b1001001111011011111 /
b1010011 :
b10000111 7
b110000111001001111011011111 5
b11101 (
b11011111100100011000110100 &
b11011111100100011000110100 +
b1111001111001110010000100 %
b1111001111001110010000100 *
1$
#335
0$
#340
b100100011000110100 4
b1100100011000110100 A
b11011111100100011000110100 !
b11011111100100011000110100 @
b100100011000110100 0
b101111 -
b11011111 <
b11011111 3
b11011111100100011000110100 >
b1100100011000110100 =
b1100100011000110100 1
b11011111100100011000110100 2
b11110010101111111100000 ;
b101001101110100000111101010 6
b1100100011000110100 /
b1100110 :
b11011111 7
b0 9
b11011111100100011000110100 5
b11110 (
b101001101110100000111101010 &
b101001101110100000111101010 +
b11110010101111111100000 %
b11110010101111111100000 *
1$
#345
0$
#350
b110100000111101010 4
b1 8
b1110100000111101010 A
b101001101110100000111101010 !
b101001101110100000111101010 @
b110100000111101010 0
b10010 -
b1001101 <
b1001101 3
b101001101110100000111101010 >
b1110100000111101010 1
b1110100000111101010 =
b101001101110100000111101010 2
b100101000111110110011000011 ;
b111010101000110001110000 6
1,
b1110100000111101010 /
b101111 :
b1001101 7
b101001101110100000111101010 5
b11111 (
b100101000111110110011000011 &
b100101000111110110011000011 +
b111010101000110001110000 %
b111010101000110001110000 *
1$
#355
0$
#360
b101000110001101111 4
b1101000110001101111 A
b111010101000110001101111 !
b111010101000110001101111 @
b1000110100010011 8
b101000110001110001 0
b11 -
b111010 <
b111010 3
b111010101000110001101111 >
b1101000110001101111 =
b1101000110001110001 1
b111010101000110001110001 2
b11101100000110100010011101 ;
b11101111111000100011100000 6
b1 .
b1101000110001110000 /
b10010 :
b111010 7
b10000000000000000001 9
b111010101000110001110000 5
b100000 (
b11101100000110100010011101 &
b11101100000110100010011101 +
b11101111111000100011100000 %
b11101111111000100011100000 *
1$
#365
0$
#370
b101111101111001101 4
b11101111101111101111001101 >
b11110000000000101011111001 2
b1101111101111001101 A
b0 8
b101011111001 0
b101111 -
b11110000000000101011111001 !
b11110000000000101011111001 @
b11101111 <
b11110000 3
b10000001010111110011 1
b1101111101111001101 =
b10010100100001010101000010 ;
b11000011001011111110110011 6
0,
b1000110100010011 .
b1111000100011100000 /
b11 :
b11101111 7
b1000110100010011 9
b11101111111000100011100000 5
b100001 (
b11000011001011111110110011 &
b11000011001011111110110011 +
b10010100100001010101000010 %
b10010100100001010101000010 *
1$
#375
0$
#380
b11000011001011111110110011 !
b11000011001011111110110011 @
b1011111110110011 4
b11000011001011111110110011 >
b11000011001011111110110011 2
b1001011111110110011 A
b1011111110110011 0
b1011001 -
b11000011 <
b11000011 3
b1001011111110110011 =
b1001011111110110011 1
b100111000110101000100000010 ;
b110010001110010001000010000 6
b0 .
b1001011111110110011 /
b101111 :
b11000011 7
b0 9
b11000011001011111110110011 5
b100010 (
b110010001110010001000010000 &
b110010001110010001000010000 +
b100111000110101000100000010 %
b100111000110101000100000010 *
1$
#385
0$
#390
b110010001000010000 4
b1110010001000010000 A
b110010001110010001000010000 !
b110010001110010001000010000 @
b110010001000010000 0
b10011100 -
b10010001 <
b10010001 3
b110010001110010001000010000 >
b1110010001000010000 1
b1110010001000010000 =
b110010001110010001000010000 2
b100111001010000001111100001 ;
b11010101000011110010001011 6
b1110010001000010000 /
b1011001 :
b10010001 7
b10000000000000000000 9
b110010001110010001000010000 5
b100011 (
b11010101000011110010001011 &
b11010101000011110010001011 +
b100111001010000001111100001 %
b100111001010000001111100001 *
1$
#395
0$
#400
b11110010001011 4
b1000011110010001011 A
b11010101000011110010001011 !
b11010101000011110010001011 @
b11110010001011 0
b1000010 -
b11010101 <
b11010101 3
b11010101000011110010001011 >
b1000011110010001011 =
b1000011110010001011 1
b11010101000011110010001011 2
b10000000010010010111101001 ;
b111000010101011110110101101 6
1,
b1000011110010001011 /
b10011100 :
b11010101 7
b11010101000011110010001011 5
b100100 (
b10000000010010010111101001 &
b10000000010010010111101001 +
b111000010101011110110101101 %
b111000010101011110110101101 *
1$
#405
0$
#410
b101011110110101101 4
b1101011110110101101 A
b111000010101011110110101101 !
b111000010101011110110101101 @
b101011110110101101 0
b111110 -
b11000010 <
b11000010 3
b111000010101011110110101101 >
b1101011110110101101 1
b1101011110110101101 =
b111000010101011110110101101 2
b10110001001100000000101100 ;
b11101111001100110001111110 6
b1101011110110101101 /
b1000010 :
b11000010 7
b0 9
b111000010101011110110101101 5
b100101 (
b11101111001100110001111110 &
b11101111001100110001111110 +
b10110001001100000000101100 %
b10110001001100000000101100 *
1$
#415
0$
