rtl/FpAdd.v
//--------------------------------------------------------------------
// Author: Omkar Girish Kamath (201EC140)
// Date: October 1st, 2023
// Module Name: FpAdd
// Module Description: Implements the custom 27-bit floating point
//                     adder where MSB is sign bit, next 8-bits are
//                     exponent in excess 127 and last 18-bits are ma-
//                     ntissa.
//--------------------------------------------------------------------

`define SIGN 26
`define EXP 25:18
`define MANT 17:0


module FpAdd (
              clk,             // replace string with clock
              in1,          // replace string with fp_in1
              in2,          // replace string with fp_in2
              sum,          // replace string with fp_sum
              rst
              );

   //--------------------------------------------------------------------
   // Inputs
   //--------------------------------------------------------------------
   input wire clk;
   input wire [26:0] in1;
   input wire [26:0] in2;
   input wire        rst;
   
   //--------------------------------------------------------------------
   // Outputs
   //--------------------------------------------------------------------
   output reg [26:0] sum;

   //--------------------------------------------------------------------
   // Internals
   //--------------------------------------------------------------------
   parameter sign = 26;
   parameter ex_end = 25;
   parameter ex_st = 18;
   parameter ma_end = 17;
   parameter ma_st = 0;

   //--------------------------------------------------------------------
   // First Stage
   //--------------------------------------------------------------------
   
   //--------------------------------------------------------------------
   // Finding greater number among the 2
   //--------------------------------------------------------------------
   reg [`SIGN:0] greater;
   reg [`SIGN:0] smaller;

   always @(*)
     begin
        if (in1[`EXP] > in2[`EXP])
          begin
             greater <= in1;
             smaller <= in2;
          end
        else
          if (in1[`EXP] == in2[`EXP] && in1[`MANT] > in2[`MANT])
            begin
               greater <= in1;
               smaller <= in2;
            end
          else
            begin
               greater <= in2;
               smaller <= in1;
            end
     end // always @ (*)
   
   
   //--------------------------------------------------------------------
   // Net smaller value for arithmetic
   //--------------------------------------------------------------------
   reg [18:0] net_small;
   wire [`EXP] small_shift;
   
   assign small_shift = greater[`EXP] - smaller[`EXP];
   
   always @(*)
     begin
        if (greater[`EXP] - smaller[`EXP] <= 5'd18)
          begin
             net_small <= {1'b1,smaller[`MANT]} >> (small_shift);
          end
        else
          begin
             net_small <= 'b0;
          end
     end // always @ (*)


   //--------------------------------------------------------------------
   // Pipeline Register's
   //--------------------------------------------------------------------
   reg [`SIGN:0] gr;
   reg [19:0] sm;
   reg [`EXP]    net_expt;
   reg [`EXP]    sm_shift;
   
   always @(posedge clk )
     begin
        if (rst == 'b0)
          begin
             gr <= 'b0;
             sm <= 'b0;
             net_expt <= 'b0;
             sm_shift <= 'b0;
          end 
        else
           begin
             gr <= greater;
             sm <= {smaller[`SIGN],net_small}; // check for sm
             net_expt <= greater[`EXP];
             sm_shift <= small_shift;
          end    
     end

   
   //--------------------------------------------------------------------
   // Second Stage
   //--------------------------------------------------------------------
   
   //--------------------------------------------------------------------
   // Deciding Addition or Subtraction
   //--------------------------------------------------------------------
   wire sub;
   assign sub = (gr[`SIGN] ^ sm[19]);
   

   //--------------------------------------------------------------------
   // Addition
   //--------------------------------------------------------------------
   
   //--------------------------------------------------------------------
   // Addition Output
   //--------------------------------------------------------------------
   reg [19:0] add_out;
   
   always @(*)
      begin
         add_out <= ({1'b1,gr[`MANT]} + {sm[18:0]});
      end


   //--------------------------------------------------------------------
   // net exponent adder if carry generated in addition
   //--------------------------------------------------------------------
   reg [`EXP] expt_carry;

   always @(*)
     begin
        expt_carry <= net_expt + {7'b0,add_out[19]};
     end


   //--------------------------------------------------------------------
   // result from the whole flow if sign bits of both numbers are equal
   // i.e addition of their magnitudes
   //--------------------------------------------------------------------
   reg [26:0] add_result;
   
   wire [17:0] final_add = (add_out[19]) ? 
               {add_out[18:1]} : add_out[17:0];
   

   always @(*)
     begin
        add_result <= {gr[`SIGN],expt_carry,final_add};
     end // always @ (*)

   
   //--------------------------------------------------------------------
   // Subtraction
   //--------------------------------------------------------------------
   
   //--------------------------------------------------------------------
   // Subtraction Output
   //--------------------------------------------------------------------
   reg [18:0] sub_out;

   always @(*)
     begin
        sub_out <= {1'b1,gr[`MANT]} - sm[18:0];
     end

   //--------------------------------------------------------------------
   // Exponent Difference after subtraction Generator
   //--------------------------------------------------------------------
   reg [4:0] sub_shift;
      always @(*)
     begin
        casex (sub_out)
          19'b1XXXXXXXXXXXXXXXXXX: sub_shift <= 5'd0;
          19'b01XXXXXXXXXXXXXXXXX: sub_shift <= 5'd1;
          19'b001XXXXXXXXXXXXXXXX: sub_shift <= 5'd2;
          19'b0001XXXXXXXXXXXXXXX: sub_shift <= 5'd3;
          19'b00001XXXXXXXXXXXXXX: sub_shift <= 5'd4;
          19'b000001XXXXXXXXXXXXX: sub_shift <= 5'd5;
          19'b0000001XXXXXXXXXXXX: sub_shift <= 5'd6;
          19'b00000001XXXXXXXXXXX: sub_shift <= 5'd7;
          19'b000000001XXXXXXXXXX: sub_shift <= 5'd8;
          19'b0000000001XXXXXXXXX: sub_shift <= 5'd9;
          19'b00000000001XXXXXXXX: sub_shift <= 5'd10;
          19'b000000000001XXXXXXX: sub_shift <= 5'd11;
          19'b0000000000001XXXXXX: sub_shift <= 5'd12;
          19'b00000000000001XXXXX: sub_shift <= 5'd13;
          19'b000000000000001XXXX: sub_shift <= 5'd14;
          19'b0000000000000001XXX: sub_shift <= 5'd15;
          19'b00000000000000001XX: sub_shift <= 5'd16;
          19'b000000000000000001X: sub_shift <= 5'd17;
          19'b0000000000000000001: sub_shift <= 5'd18;
          19'b0000000000000000000: sub_shift <= 5'd19;
          default:                sub_shift <= 5'd0;
        endcase
     end // always @ (*)

  
   //--------------------------------------------------------------------
   // Calculating net exponent
   //--------------------------------------------------------------------
   reg [7:0] sub_expt;
   
   always @(*)
     begin
        sub_expt <= net_expt - {3'b0,sub_shift};
     end
   

   //--------------------------------------------------------------------
   // Calculating Final Subtraction Out after shift
   //--------------------------------------------------------------------
   reg [17:0] final_sub;
   reg [18:0] temp_sub;
   always @(*)
     begin
        temp_sub <= (sub_out << sub_shift);
        final_sub <= temp_sub[17:0];
     end
   //--------------------------------------------------------------------
   // Calculating Final Subtraction Result
   //--------------------------------------------------------------------
   reg [26:0] sub_result;

   always @(*)
     begin
        sub_result <= {gr[`SIGN],sub_expt,final_sub};
     end

   //--------------------------------------------------------------------
   // Calculating Final Subtraction Result
   //--------------------------------------------------------------------
   always @(*)
     begin
        if (sub)
          begin
             sum <= sub_result;
          end
        else
          begin
             sum <= add_result;
          end
     end

   //--------------------------------------------------------------------
   // Test code (not part of the RTL)
   //--------------------------------------------------------------------
   // always @(*)
   //   begin
   //      sum <= add_result;
   //  end
   wire [18:0] sm_mant = sm[18:0];
   wire [18:0] gr_mant = {1'b1,gr[`MANT]};
   
endmodule

prac/FpAdd_tb.v
module FpAdd_tb;
   reg [26:0] tst_in1;
   reg [26:0] tst_in2;
   reg        tst_clk;
   reg        tst_rst;
   wire [26:0] tst_out;
   reg [31:0]  fh;
   reg [31:0]  oh;
   reg [31:0]  file_result;
   integer     count;
   integer     total;
   
   reg [26:0]  vec1 [1023:0];
   reg [26:0]  vec2 [1023:0];
   
   initial
     begin
        fh = $fopen("/home/omkar/projects/grav_sim/test/Fp_Add_tstvec.txt","r");
        //oh = $fopen("../run/FpAddtemp.txt","w");
     end

   
   FpAdd dut (
              .clk(tst_clk),
              .rst(tst_rst),
              .in1(tst_in1),
              .in2(tst_in2),
              .sum(tst_out)
              );
   
   always
     begin
        tst_clk <= 1'b1;
        #5;
        tst_clk <= 1'b0;
        #5;
     end
   
   always @(posedge tst_clk)
     begin
        if (tst_rst == 'b1)
          begin
             tst_in1 <= vec1[count];
             tst_in2 <= vec2[count];
             $display("%b",tst_out);
             count <= count + 1;
             if (count == total)
               begin
                  $finish;
               end
          end
     end
   


   
   initial
     begin
        $dumpvars;
        count = 0;
        while (!$feof(fh))
          begin
             file_result = $fscanf(fh,"%b %b",vec1[count],vec2[count]);
             count = count + 1;
          end
        total <= count;
        count <= 0;
        tst_rst = 'b0;
        repeat (5)
          begin
             @ (posedge tst_clk);
          end
        //#50;
        tst_rst <= 'b1;
        
        #1000;
        $finish;
        
        
     end

endmodule

run/dump.vcd
$date
	Wed Oct 25 02:34:25 2023
$end
$version
	Icarus Verilog
$end
$timescale
	1s
$end
$scope module FpAdd_tb $end
$var wire 27 ! tst_out [26:0] $end
$var reg 32 " fh [31:0] $end
$var reg 32 # file_result [31:0] $end
$var reg 1 $ tst_clk $end
$var reg 27 % tst_in1 [26:0] $end
$var reg 27 & tst_in2 [26:0] $end
$var reg 1 ' tst_rst $end
$var integer 32 ( count [31:0] $end
$var integer 32 ) total [31:0] $end
$scope module dut $end
$var wire 1 $ clk $end
$var wire 27 * in1 [26:0] $end
$var wire 27 + in2 [26:0] $end
$var wire 1 ' rst $end
$var wire 1 , sub $end
$var wire 8 - small_shift [25:18] $end
$var wire 19 . sm_mant [18:0] $end
$var wire 19 / gr_mant [18:0] $end
$var wire 18 0 final_add [17:0] $end
$var reg 20 1 add_out [19:0] $end
$var reg 27 2 add_result [26:0] $end
$var reg 8 3 expt_carry [25:18] $end
$var reg 18 4 final_sub [17:0] $end
$var reg 27 5 gr [26:0] $end
$var reg 27 6 greater [26:0] $end
$var reg 8 7 net_expt [25:18] $end
$var reg 19 8 net_small [18:0] $end
$var reg 20 9 sm [19:0] $end
$var reg 8 : sm_shift [25:18] $end
$var reg 27 ; smaller [26:0] $end
$var reg 8 < sub_expt [7:0] $end
$var reg 19 = sub_out [18:0] $end
$var reg 27 > sub_result [26:0] $end
$var reg 5 ? sub_shift [4:0] $end
$var reg 27 @ sum [26:0] $end
$var reg 19 A temp_sub [18:0] $end
$upscope $end
$upscope $end
$enddefinitions $end
#0
$dumpvars
b1000000000000000000 A
b0 @
b0 ?
b0 >
b1000000000000000000 =
b0 <
bx ;
b0 :
b0 9
bx 8
b0 7
bx 6
b0 5
b0 4
b0 3
b0 2
b1000000000000000000 1
b0 0
b1000000000000000000 /
b0 .
bx -
0,
bx +
bx *
b1111101001 )
b0 (
0'
bx &
bx %
1$
b0 #
b10000000000000000000000000000011 "
b0 !
$end
#5
0$
#10
1$
#15
0$
#20
1$
#25
0$
#30
1$
#35
0$
#40
1'
1$
#45
0$
#50
bx 4
bx A
bx !
bx @
b0 8
bx 0
b1110010 -
bx <
bx 3
bx >
bx 1
bx =
bx 2
b1010000011100111100110011 ;
b11000010001001100110111011 6
x,
bx .
b1xxxxxxxxxxxxxxxxxx /
bx :
bx 7
bx 9
bx 5
b1 (
b11000010001001100110111011 &
b11000010001001100110111011 +
b1010000011100111100110011 %
b1010000011100111100110011 *
1$
#55
0$
#60
b1001100110111011 4
b1001001100110111011 A
b11000010 3
b11000010001001100110111011 !
b11000010001001100110111011 @
b1001100110111011 0
b10110 -
b11000010 <
b11000010001001100110111011 >
b1001001100110111011 =
b1001001100110111011 1
b11000010001001100110111011 2
b100011100100011011111111011 ;
b100110010000110011100111100 6
0,
b0 .
b1001001100110111011 /
b1110010 :
b11000010 7
b0 9
b11000010001001100110111011 5
b10 (
b100110010000110011100111100 &
b100110010000110011100111100 +
b100011100100011011111111011 %
b100011100100011011111111011 *
1$
#65
0$
#70
b110011100111100 4
b1000110011100111100 A
b100110010000110011100111100 !
b100110010000110011100111100 @
b110011100111100 0
b11011 -
b110010 <
b110010 3
b100110010000110011100111100 >
b1000110011100111100 1
b1000110011100111100 =
b100110010000110011100111100 2
b101000111111101010011101 ;
b1000011100100011011011100 6
b1000110011100111100 /
b10110 :
b110010 7
b10000000000000000000 9
b100110010000110011100111100 5
b11 (
b1000011100100011011011100 &
b1000011100100011011011100 +
b101000111111101010011101 %
b101000111111101010011101 *
1$
#75
0$
#80
b100100011011011100 4
b1100100011011011100 A
b1000011100100011011011100 !
b1000011100100011011011100 @
b100100011011011100 0
b101111 -
b1000011 <
b1000011 3
b1000011100100011011011100 >
b1100100011011011100 =
b1100100011011011100 1
b1000011100100011011011100 2
b110100000000111101011010000 ;
b111001111101010111110001001 6
b1100100011011011100 /
b11011 :
b1000011 7
b0 9
b1000011100100011011011100 5
b100 (
b111001111101010111110001001 &
b111001111101010111110001001 +
b110100000000111101011010000 %
b110100000000111101011010000 *
1$
#85
0$
#90
b101010111110001001 4
b1101010111110001001 A
b111001111101010111110001001 !
b111001111101010111110001001 @
b101010111110001001 0
b110110 -
b11001111 <
b11001111 3
b111001111101010111110001001 >
b1101010111110001001 1
b1101010111110001001 =
b111001111101010111110001001 2
b100010101001110110101000001 ;
b101001011101011010010010010 6
b1101010111110001001 /
b101111 :
b11001111 7
b10000000000000000000 9
b111001111101010111110001001 5
b101 (
b101001011101011010010010010 &
b101001011101011010010010010 +
b100010101001110110101000001 %
b100010101001110110101000001 *
1$
#95
0$
#100
b101001011101011010010010010 !
b101001011101011010010010010 @
b101011010010010010 4
b101001011101011010010010010 >
b101001011101011010010010010 2
b1101011010010010010 A
b101011010010010010 0
b10000100 -
b1001011 <
b1001011 3
b1101011010010010010 =
b1101011010010010010 1
b100001100001111011000010111 ;
b110010000001111010101110101 6
b1101011010010010010 /
b110110 :
b1001011 7
b101001011101011010010010010 5
b110 (
b100001100001111011000010111 &
b100001100001111011000010111 +
b110010000001111010101110101 %
b110010000001111010101110101 *
1$
#105
0$
#110
b110010000001111010101110101 !
b110010000001111010101110101 @
b1111010101110101 4
b110010000001111010101110101 >
b110010000001111010101110101 2
b1001111010101110101 A
b1111010101110101 0
b10110010 -
b10010000 <
b10010000 3
b1001111010101110101 1
b1001111010101110101 =
b100000101000101110001110101 ;
b10110111111111100111001110 6
b1001111010101110101 /
b10000100 :
b10010000 7
b110010000001111010101110101 5
b111 (
b100000101000101110001110101 &
b100000101000101110001110101 +
b10110111111111100111001110 %
b10110111111111100111001110 *
1$
#115
0$
#120
b111111100111001110 4
b110011101000 8
b1111111100111001110 A
b10110111111111100111001110 !
b10110111111111100111001110 @
b111111100111001110 0
b111 -
b10110111 <
b10110111 3
b10110111111111100111001110 >
b1111111100111001110 =
b1111111100111001110 1
b10110111111111100111001110 2
b11101110100111010000101101 ;
b111110101111011011001100101 6
1,
b1111111100111001110 /
b10110010 :
b10110111 7
b10110111111111100111001110 5
b1000 (
b111110101111011011001100101 &
b111110101111011011001100101 +
b11101110100111010000101101 %
b11101110100111010000101101 *
1$
#125
0$
#130
b111010100101111101 4
b1111010100101111101 A
b111110101111010100101111101 !
b111110101111010100101111101 @
b0 8
b111100001101001101 0
b10101 -
b11110101 <
b11110101 3
b111110101111010100101111101 >
b1111100001101001101 1
b1111010100101111101 =
b111110101111100001101001101 2
b110011011011101101111000110 ;
b110110000111101110111000010 6
b110011101000 .
b1111011011001100101 /
b111 :
b11110101 7
b110011101000 9
b111110101111011011001100101 5
b1001 (
b110110000111101110111000010 &
b110110000111101110111000010 +
b110011011011101101111000110 %
b110011011011101101111000110 *
1$
#135
0$
#140
b111101110111000010 4
b110110000111101110111000010 >
b110110000111101110111000010 2
b1111101110111000010 A
b111101110111000010 0
b1101011 -
b110110000111101110111000010 !
b110110000111101110111000010 @
b10110000 <
b10110000 3
b1111101110111000010 =
b1111101110111000010 1
b1101110111010001010111111 ;
b111011001000010101000101000 6
0,
b0 .
b1111101110111000010 /
b10101 :
b10110000 7
b10000000000000000000 9
b110110000111101110111000010 5
b1010 (
b1101110111010001010111111 &
b1101110111010001010111111 +
b111011001000010101000101000 %
b111011001000010101000101000 *
1$
#145
0$
#150
b111011001000010101000101000 !
b111011001000010101000101000 @
b10101000101000 4
b111011001000010101000101000 >
b111011001000010101000101000 2
b1000010101000101000 A
b10101000101000 0
b1110100 -
b11011001 <
b11011001 3
b1000010101000101000 1
b1000010101000101000 =
b1001110100110111001010101 ;
b11000010100100111111111000 6
1,
b1000010101000101000 /
b1101011 :
b11011001 7
b0 9
b111011001000010101000101000 5
b1011 (
b11000010100100111111111000 &
b11000010100100111111111000 +
b1001110100110111001010101 %
b1001110100110111001010101 *
1$
#155
0$
#160
b100100111111111000 4
b1100100111111111000 A
b11000010100100111111111000 !
b11000010100100111111111000 @
b100100111111111000 0
b10101001 -
b11000010 <
b11000010 3
b11000010100100111111111000 >
b1100100111111111000 =
b1100100111111111000 1
b11000010100100111111111000 2
b11000011110111010001101 ;
b11000001011011000010111001 6
0,
b1100100111111111000 /
b1110100 :
b11000010 7
b11000010100100111111111000 5
b1100 (
b11000011110111010001101 &
b11000011110111010001101 +
b11000001011011000010111001 %
b11000001011011000010111001 *
1$
#165
0$
#170
b11000001011011000010111001 !
b11000001011011000010111001 @
b11011000010111001 4
b11000001011011000010111001 >
b11000001011011000010111001 2
b1011011000010111001 A
b11011000010111001 0
b11010101 -
b11000001 <
b11000001 3
b1011011000010111001 1
b1011011000010111001 =
b100011010000000111111001001 ;
b11101111101001111001001000 6
b1011011000010111001 /
b10101001 :
b11000001 7
b11000001011011000010111001 5
b1101 (
b100011010000000111111001001 &
b100011010000000111111001001 +
b11101111101001111001001000 %
b11101111101001111001001000 *
1$
#175
0$
#180
b11101111101001111001001000 !
b11101111101001111001001000 @
b101001111001001000 4
b11101111101001111001001000 >
b11101111101001111001001000 2
b1101001111001001000 A
b101001111001001000 0
b11000000 -
b11101111 <
b11101111 3
b1101001111001001000 =
b1101001111001001000 1
b100101101011011000101010011 ;
b111101101001000011000011110 6
1,
b1101001111001001000 /
b11010101 :
b11101111 7
b10000000000000000000 9
b11101111101001111001001000 5
b1110 (
b100101101011011000101010011 &
b100101101011011000101010011 +
b111101101001000011000011110 %
b111101101001000011000011110 *
1$
#185
0$
#190
b1000011000011110 4
b1001000011000011110 A
b111101101001000011000011110 !
b111101101001000011000011110 @
b1000011000011110 0
b10010100 -
b11101101 <
b11101101 3
b111101101001000011000011110 >
b1001000011000011110 1
b1001000011000011110 =
b111101101001000011000011110 2
b1101000111010110010010101 ;
b111111100000010100110100101 6
0,
b1001000011000011110 /
b11000000 :
b11101101 7
b111101101001000011000011110 5
b1111 (
b1101000111010110010010101 &
b1101000111010110010010101 +
b111111100000010100110100101 %
b111111100000010100110100101 *
1$
#195
0$
#200
b111111100000010100110100101 !
b111111100000010100110100101 @
b10100110100101 4
b111111100000010100110100101 >
b111111100000010100110100101 2
b1000010100110100101 A
b10100110100101 0
b1001100 -
b11111100 <
b11111100 3
b1000010100110100101 =
b1000010100110100101 1
b10010011101100110100100011 ;
b11011111000100000000001011 6
1,
b1000010100110100101 /
b10010100 :
b11111100 7
b0 9
b111111100000010100110100101 5
b10000 (
b10010011101100110100100011 &
b10010011101100110100100011 +
b11011111000100000000001011 %
b11011111000100000000001011 *
1$
#205
0$
#210
b100000000001011 4
b1000100000000001011 A
b11011111000100000000001011 !
b11011111000100000000001011 @
b100000000001011 0
b1011001 -
b11011111 <
b11011111 3
b11011111000100000000001011 >
b1000100000000001011 1
b1000100000000001011 =
b11011111000100000000001011 2
b100000000011111111101000011 ;
b101011001010100100001011111 6
0,
b1000100000000001011 /
b1001100 :
b11011111 7
b11011111000100000000001011 5
b10001 (
b100000000011111111101000011 &
b100000000011111111101000011 +
b101011001010100100001011111 %
b101011001010100100001011111 *
1$
#215
0$
#220
b10100100001011111 4
b1010100100001011111 A
b101011001010100100001011111 !
b101011001010100100001011111 @
b10100100001011111 0
b110111 -
b1011001 <
b1011001 3
b101011001010100100001011111 >
b1010100100001011111 =
b1010100100001011111 1
b101011001010100100001011111 2
b100010010100000101001001000 ;
b101001001011001010101100110 6
b1010100100001011111 /
b1011001 :
b1011001 7
b10000000000000000000 9
b101011001010100100001011111 5
b10010 (
b101001001011001010101100110 &
b101001001011001010101100110 +
b100010010100000101001001000 %
b100010010100000101001001000 *
1$
#225
0$
#230
b101001001011001010101100110 !
b101001001011001010101100110 @
b11001010101100110 4
b101001001011001010101100110 >
b101001001011001010101100110 2
b1011001010101100110 A
b11001010101100110 0
b1010100 -
b1001001 <
b1001001 3
b1011001010101100110 1
b1011001010101100110 =
b100000101101101010111011011 ;
b1011001011100101100100010 6
b1011001010101100110 /
b110111 :
b1001001 7
b101001001011001010101100110 5
b10011 (
b100000101101101010111011011 &
b100000101101101010111011011 +
b1011001011100101100100010 %
b1011001011100101100100010 *
1$
#235
0$
#240
b11100101100100010 4
b1011100101100100010 A
b1011001011100101100100010 !
b1011001011100101100100010 @
b11100101100100010 0
b100101 -
b1011001 <
b1011001 3
b1011001011100101100100010 >
b1011100101100100010 =
b1011100101100100010 1
b1011001011100101100100010 2
b10111010101110001001000010 ;
b111011111110001111100010110 6
1,
b1011100101100100010 /
b1010100 :
b1011001 7
b1011001011100101100100010 5
b10100 (
b111011111110001111100010110 &
b111011111110001111100010110 +
b10111010101110001001000010 %
b10111010101110001001000010 *
1$
#245
0$
#250
b110001111100010110 4
b1110001111100010110 A
b111011111110001111100010110 !
b111011111110001111100010110 @
b110001111100010110 0
b1111010 -
b11011111 <
b11011111 3
b111011111110001111100010110 >
b1110001111100010110 1
b1110001111100010110 =
b111011111110001111100010110 2
b101001101001111111111001010 ;
b11000111111010110000110111 6
b1110001111100010110 /
b100101 :
b11011111 7
b0 9
b111011111110001111100010110 5
b10101 (
b101001101001111111111001010 &
b101001101001111111111001010 +
b11000111111010110000110111 %
b11000111111010110000110111 *
1$
#255
0$
#260
b111010110000110111 4
b1111010110000110111 A
b11000111111010110000110111 !
b11000111111010110000110111 @
b111010110000110111 0
b1010111 -
b11000111 <
b11000111 3
b11000111111010110000110111 >
b1111010110000110111 =
b1111010110000110111 1
b11000111111010110000110111 2
b10011100100100000011110011 ;
b11110011110011011001011110 6
b1111010110000110111 /
b1111010 :
b11000111 7
b10000000000000000000 9
b11000111111010110000110111 5
b10110 (
b10011100100100000011110011 &
b10011100100100000011110011 +
b11110011110011011001011110 %
b11110011110011011001011110 *
1$
#265
0$
#270
b11110011110011011001011110 !
b11110011110011011001011110 @
b110011011001011110 4
b11110011110011011001011110 >
b11110011110011011001011110 2
b1110011011001011110 A
b110011011001011110 0
b1101001 -
b11110011 <
b11110011 3
b1110011011001011110 1
b1110011011001011110 =
b101001010110010000011111111 ;
b10110011000100100001000001 6
0,
b1110011011001011110 /
b1010111 :
b11110011 7
b0 9
b11110011110011011001011110 5
b10111 (
b10110011000100100001000001 &
b10110011000100100001000001 +
b101001010110010000011111111 %
b101001010110010000011111111 *
1$
#275
0$
#280
b10110011000100100001000001 !
b10110011000100100001000001 @
b100100001000001 4
b10110011000100100001000001 >
b10110011000100100001000001 2
b1000100100001000001 A
b100100001000001 0
b10011011 -
b10110011 <
b10110011 3
b1000100100001000001 =
b1000100100001000001 1
b101000011100010101000111011 ;
b11011110011001001100001111 6
1,
b1000100100001000001 /
b1101001 :
b10110011 7
b10000000000000000000 9
b10110011000100100001000001 5
b11000 (
b101000011100010101000111011 &
b101000011100010101000111011 +
b11011110011001001100001111 %
b11011110011001001100001111 *
1$
#285
0$
#290
b11011110011001001100001111 !
b11011110011001001100001111 @
b11001001100001111 4
b11011110011001001100001111 >
b11011110011001001100001111 2
b1011001001100001111 A
b11001001100001111 0
b1011011 -
b11011110 <
b11011110 3
b1011001001100001111 1
b1011001001100001111 =
b1010010111101101101000111 ;
b110101101110101001010111100 6
b1011001001100001111 /
b10011011 :
b11011110 7
b11011110011001001100001111 5
b11001 (
b110101101110101001010111100 &
b110101101110101001010111100 +
b1010010111101101101000111 %
b1010010111101101101000111 *
1$
#295
0$
#300
b110101001010111100 4
b1110101001010111100 A
b110101101110101001010111100 !
b110101101110101001010111100 @
b110101001010111100 0
b11100 -
b10101101 <
b10101101 3
b110101101110101001010111100 >
b1110101001010111100 =
b1110101001010111100 1
b110101101110101001010111100 2
b101101010110011110010110111 ;
b10000110111100101001100000 6
b1110101001010111100 /
b1011011 :
b10101101 7
b0 9
b110101101110101001010111100 5
b11010 (
b10000110111100101001100000 &
b10000110111100101001100000 +
b101101010110011110010110111 %
b101101010110011110010110111 *
1$
#305
0$
#310
b111100101001100000 4
b1111100101001100000 A
b10000110111100101001100000 !
b10000110111100101001100000 @
b111100101001100000 0
b101100 -
b10000110 <
b10000110 3
b10000110111100101001100000 >
b1111100101001100000 1
b1111100101001100000 =
b10000110111100101001100000 2
b111101111110001001000101 ;
b1101001111010000001111001 6
b1111100101001100000 /
b11100 :
b10000110 7
b10000000000000000000 9
b10000110111100101001100000 5
b11011 (
b111101111110001001000101 &
b111101111110001001000101 +
b1101001111010000001111001 %
b1101001111010000001111001 *
1$
#315
0$
#320
b1101001111010000001111001 !
b1101001111010000001111001 @
b111010000001111001 4
b1101001111010000001111001 >
b1101001111010000001111001 2
b1111010000001111001 A
b111010000001111001 0
b1101100 -
b1101001 <
b1101001 3
b1111010000001111001 =
b1111010000001111001 1
b101110100101011111010110 ;
b10011010100001010011100111 6
0,
b1111010000001111001 /
b101100 :
b1101001 7
b0 9
b1101001111010000001111001 5
b11100 (
b10011010100001010011100111 &
b10011010100001010011100111 +
b101110100101011111010110 %
b101110100101011111010110 *
1$
#325
0$
#330
b10011010100001010011100111 !
b10011010100001010011100111 @
b100001010011100111 4
b10011010100001010011100111 >
b10011010100001010011100111 2
b1100001010011100111 A
b100001010011100111 0
b10110100 -
b10011010 <
b10011010 3
b1100001010011100111 1
b1100001010011100111 =
b100010001000000010101111110 ;
b111000101000010100000111001 6
b1100001010011100111 /
b1101100 :
b10011010 7
b10011010100001010011100111 5
b11101 (
b111000101000010100000111001 &
b111000101000010100000111001 +
b100010001000000010101111110 %
b100010001000000010101111110 *
1$
#335
0$
#340
b10100000111001 4
b1000010100000111001 A
b111000101000010100000111001 !
b111000101000010100000111001 @
b10100000111001 0
b100001 -
b11000101 <
b11000101 3
b111000101000010100000111001 >
b1000010100000111001 =
b1000010100000111001 1
b111000101000010100000111001 2
b11110001101000010101000 ;
b100111111011011111011110000 6
b1000010100000111001 /
b10110100 :
b11000101 7
b10000000000000000000 9
b111000101000010100000111001 5
b11110 (
b100111111011011111011110000 &
b100111111011011111011110000 +
b11110001101000010101000 %
b11110001101000010101000 *
1$
#345
0$
#350
b100111111011011111011110000 !
b100111111011011111011110000 @
b11011111011110000 4
b100111111011011111011110000 >
b100111111011011111011110000 2
b1011011111011110000 A
b11011111011110000 0
b110010 -
b111111 <
b111111 3
b1011011111011110000 1
b1011011111011110000 =
b110100011010111000011010100 ;
b111010101110001000110000111 6
1,
b1011011111011110000 /
b100001 :
b111111 7
b0 9
b100111111011011111011110000 5
b11111 (
b110100011010111000011010100 &
b110100011010111000011010100 +
b111010101110001000110000111 %
b111010101110001000110000111 *
1$
#355
0$
#360
b111010101110001000110000111 !
b111010101110001000110000111 @
b110001000110000111 4
b111010101110001000110000111 >
b111010101110001000110000111 2
b1110001000110000111 A
b110001000110000111 0
b11011 -
b11010101 <
b11010101 3
b1110001000110000111 =
b1110001000110000111 1
b101000111111000110100100011 ;
b1100010100110000100100010 6
0,
b1110001000110000111 /
b110010 :
b11010101 7
b10000000000000000000 9
b111010101110001000110000111 5
b100000 (
b1100010100110000100100010 &
b1100010100110000100100010 +
b101000111111000110100100011 %
b101000111111000110100100011 *
1$
#365
0$
#370
b100110000100100010 4
b1100110000100100010 A
b1100010100110000100100010 !
b1100010100110000100100010 @
b100110000100100010 0
b101100 -
b1100010 <
b1100010 3
b1100010100110000100100010 >
b1100110000100100010 1
b1100110000100100010 =
b1100010100110000100100010 2
b1100100001000100000000111 ;
b10010000111000001101100101 6
1,
b1100110000100100010 /
b11011 :
b1100010 7
b1100010100110000100100010 5
b100001 (
b1100100001000100000000111 &
b1100100001000100000000111 +
b10010000111000001101100101 %
b10010000111000001101100101 *
1$
#375
0$
#380
b10010000111000001101100101 !
b10010000111000001101100101 @
b111000001101100101 4
b10010000111000001101100101 >
b10010000111000001101100101 2
b1111000001101100101 A
b111000001101100101 0
b1100000 -
b10010000 <
b10010000 3
b1111000001101100101 =
b1111000001101100101 1
b100111000111001110110110000 ;
b10011000111101010000011110 6
0,
b1111000001101100101 /
b101100 :
b10010000 7
b0 9
b10010000111000001101100101 5
b100010 (
b10011000111101010000011110 &
b10011000111101010000011110 +
b100111000111001110110110000 %
b100111000111001110110110000 *
1$
#385
0$
#390
b10011000111101010000011110 !
b10011000111101010000011110 @
b111101010000011110 4
b10011000111101010000011110 >
b10011000111101010000011110 2
b1111101010000011110 A
b111101010000011110 0
b1111100 -
b10011000 <
b10011000 3
b1111101010000011110 1
b1111101010000011110 =
b100010010110001100001011110 ;
b110001110000110000010000010 6
1,
b1111101010000011110 /
b1100000 :
b10011000 7
b10000000000000000000 9
b10011000111101010000011110 5
b100011 (
b100010010110001100001011110 &
b100010010110001100001011110 +
b110001110000110000010000010 %
b110001110000110000010000010 *
1$
#395
0$
#400
b110000010000010 4
b1000110000010000010 A
b110001110000110000010000010 !
b110001110000110000010000010 @
b110000010000010 0
b1110001 -
b10001110 <
b10001110 3
b110001110000110000010000010 >
b1000110000010000010 =
b1000110000010000010 1
b110001110000110000010000010 2
b101010011001010110000100100 ;
b111000100001110001011101111 6
0,
b1000110000010000010 /
b1111100 :
b10001110 7
b110001110000110000010000010 5
b100100 (
b111000100001110001011101111 &
b111000100001110001011101111 +
b101010011001010110000100100 %
b101010011001010110000100100 *
1$
#405
0$
#410
b111000100001110001011101111 !
b111000100001110001011101111 @
b1110001011101111 4
b111000100001110001011101111 >
b111000100001110001011101111 2
b1001110001011101111 A
b1110001011101111 0
b1001001 -
b11000100 <
b11000100 3
b1001110001011101111 1
b1001110001011101111 =
b110011111110011110111100100 ;
b11101000011000111011000010 6
b1001110001011101111 /
b1110001 :
b11000100 7
b111000100001110001011101111 5
b100101 (
b110011111110011110111100100 &
b110011111110011110111100100 +
b11101000011000111011000010 %
b11101000011000111011000010 *
1$
#415
0$
